[{"id":"346445","latitude":"-1.24361110","longitude":"15.26222220","name":"Aba"},{"id":"346446","latitude":"-1.24361110","longitude":"15.26222220","name":"Aba I"},{"id":"346448","latitude":"-1.33972220","longitude":"15.52083330","name":"Abala"},{"id":"346452","latitude":"-2.40861110","longitude":"14.71250000","name":"Abala-Ndolo"},{"id":"346456","latitude":"-1.31000000","longitude":"15.90750000","name":"Abatsambi"},{"id":"346457","latitude":"-2.40472220","longitude":"15.11111110","name":"Abba"},{"id":"346461","latitude":"-1.08833330","longitude":"15.49055560","name":"Ab\u00e9la"},{"id":"346464","latitude":"-2.35250000","longitude":"15.37638890","name":"Abi"},{"id":"346465","latitude":"-2.00444440","longitude":"15.14277780","name":"Abila"},{"id":"346466","latitude":"-2.28416670","longitude":"14.54500000","name":"Abili"},{"id":"346469","latitude":"-1.35972220","longitude":"15.98277780","name":"Abo"},{"id":"346470","latitude":"-1.23333330","longitude":"16.03333330","name":"Abogo"},{"id":"346489","latitude":"-2.66916670","longitude":"15.30500000","name":"Adzi"},{"id":"346494","latitude":"-1.65361110","longitude":"15.56833330","name":"Afou"},{"id":"346496","latitude":"-1.66250000","longitude":"15.61138890","name":"Afou-Mok\u00e9"},{"id":"346498","latitude":"-1.46027780","longitude":"15.93916670","name":"Aila"},{"id":"346500","latitude":"-1.54888890","longitude":"15.37500000","name":"Akabi"},{"id":"346501","latitude":"-1.33527780","longitude":"15.40750000","name":"Akala"},{"id":"346506","latitude":"-1.45750000","longitude":"15.86000000","name":"Akana"},{"id":"346510","latitude":"-1.34472220","longitude":"15.88166670","name":"Akao"},{"id":"346515","latitude":"-1.38333330","longitude":"16.05500000","name":"Ak\u00e9l\u00e9"},{"id":"346516","latitude":"-2.22333330","longitude":"15.02388890","name":"Ak\u00e9okou\u00e9"},{"id":"346517","latitude":"-1.50888890","longitude":"15.83722220","name":"Akiel\u00e9"},{"id":"346522","latitude":"-1.26500000","longitude":"15.84972220","name":"Akongo"},{"id":"346525","latitude":"-1.56305560","longitude":"15.06277780","name":"Akou"},{"id":"346527","latitude":"-2.50361110","longitude":"15.16805560","name":"Akoui"},{"id":"346529","latitude":"-1.98805560","longitude":"15.74722220","name":"Akouo"},{"id":"346530","latitude":"-1.10166670","longitude":"15.81388890","name":"Akousika"},{"id":"346531","latitude":"-1.10166670","longitude":"15.81388890","name":"Akoussika"},{"id":"346532","latitude":"-1.34527780","longitude":"15.65722220","name":"Ala"},{"id":"346538","latitude":"-2.35222220","longitude":"14.43666670","name":"Al\u00e9g\u00e9 Pira"},{"id":"346539","latitude":"-1.71305560","longitude":"14.99194440","name":"Al\u00e9ki"},{"id":"346541","latitude":"-1.13388890","longitude":"15.33722220","name":"Alemb\u00e9"},{"id":"346548","latitude":"-2.36611110","longitude":"15.27250000","name":"Alion"},{"id":"346553","latitude":"-2.36611110","longitude":"15.27250000","name":"Allion"},{"id":"346554","latitude":"-2.21194440","longitude":"15.03000000","name":"Ambabou"},{"id":"346555","latitude":"-1.82472220","longitude":"16.10333330","name":"Ambali"},{"id":"346561","latitude":"-1.36972220","longitude":"15.95638890","name":"Ambombongo"},{"id":"346567","latitude":"-1.79750000","longitude":"15.97861110","name":"Ambou\u00e9"},{"id":"346569","latitude":"-2.06083330","longitude":"15.63111110","name":"Ami\u00e9l\u00e9"},{"id":"346573","latitude":"-1.61750000","longitude":"14.96277780","name":"Ampaka"},{"id":"346574","latitude":"-1.62194440","longitude":"14.96527780","name":"Ampo"},{"id":"346576","latitude":"-2.21194440","longitude":"15.03000000","name":"Anbabou"},{"id":"346577","latitude":"-1.82472220","longitude":"16.10333330","name":"Anbala"},{"id":"346579","latitude":"-2.35138890","longitude":"14.46500000","name":"Anbi\u00e9l\u00e9"},{"id":"346580","latitude":"-1.36972220","longitude":"15.95638890","name":"Anbombongo"},{"id":"346607","latitude":"-1.85027780","longitude":"16.00250000","name":"Andoumou"},{"id":"346608","latitude":"-1.85027780","longitude":"16.00250000","name":"Andounou"},{"id":"346609","latitude":"-1.90638890","longitude":"15.01277780","name":"Andziem\u00e9"},{"id":"346610","latitude":"-2.00444440","longitude":"15.86888890","name":"Andzion"},{"id":"346613","latitude":"-2.30583330","longitude":"14.61750000","name":"Andzounou"},{"id":"346617","latitude":"-2.39277780","longitude":"14.48694440","name":"Angama"},{"id":"346618","latitude":"-1.70555560","longitude":"15.49055560","name":"Angao"},{"id":"346619","latitude":"-2.33194440","longitude":"14.48722220","name":"Angi\u00e9m\u00e9"},{"id":"346621","latitude":"-2.20277780","longitude":"15.03500000","name":"Ango"},{"id":"346622","latitude":"-2.17833330","longitude":"15.05361110","name":"Angoini"},{"id":"346626","latitude":"-1.77972220","longitude":"16.07444440","name":"Angouala"},{"id":"346627","latitude":"-1.78472220","longitude":"15.99805560","name":"Angou\u00e9"},{"id":"346628","latitude":"-1.88583330","longitude":"16.14805560","name":"Angou\u00e9l\u00e9"},{"id":"346629","latitude":"-1.77972220","longitude":"16.07444440","name":"Angou\u00e9li"},{"id":"346630","latitude":"-1.98666670","longitude":"16.16305560","name":"Angou\u00e9r\u00e9"},{"id":"346631","latitude":"-1.53111110","longitude":"15.86638890","name":"Angoulou I"},{"id":"346632","latitude":"-1.51305560","longitude":"15.86527780","name":"Angoulou II"},{"id":"346634","latitude":"-2.42250000","longitude":"15.08388890","name":"Anka"},{"id":"346637","latitude":"-1.59222220","longitude":"15.03222220","name":"Ankana"},{"id":"346638","latitude":"-2.17111110","longitude":"15.05527780","name":"Ankan"},{"id":"346639","latitude":"-1.67444440","longitude":"15.64916670","name":"Ankandziana II"},{"id":"346640","latitude":"-1.81500000","longitude":"16.20583330","name":"Anki"},{"id":"346641","latitude":"-1.80194440","longitude":"15.97416670","name":"Ankono"},{"id":"346642","latitude":"-2.30888890","longitude":"14.62777780","name":"Ankouadzia"},{"id":"346644","latitude":"-2.34944440","longitude":"14.49055560","name":"Ankou"},{"id":"346645","latitude":"-2.29027780","longitude":"14.51805560","name":"Ankouokari"},{"id":"346646","latitude":"-1.94166670","longitude":"16.18583330","name":"Ans\u00e9n\u00e9"},{"id":"346647","latitude":"-2.70972220","longitude":"16.19305560","name":"Antand\u00e9"},{"id":"346653","latitude":"-2.28138890","longitude":"14.52916670","name":"Antsui"},{"id":"346654","latitude":"-2.42611110","longitude":"14.41555560","name":"Antzi\u00e9m\u00e9"},{"id":"346655","latitude":"-1.81194440","longitude":"16.17777780","name":"Anzian"},{"id":"346656","latitude":"-1.51916670","longitude":"16.13722220","name":"Ap\u00e9m\u00e9"},{"id":"346660","latitude":"-2.48944440","longitude":"15.26861110","name":"Asa"},{"id":"346661","latitude":"-1.37583330","longitude":"16.18388890","name":"Asal\u00e9"},{"id":"346662","latitude":"-1.59083330","longitude":"15.73861110","name":"As\u00e9n\u00e9"},{"id":"346663","latitude":"-1.02027780","longitude":"15.39972220","name":"Aseng\u00e9"},{"id":"346666","latitude":"-1.47472220","longitude":"15.60388890","name":"Asina"},{"id":"346667","latitude":"-1.28638890","longitude":"15.75027780","name":"Asingo"},{"id":"346670","latitude":"-1.58472220","longitude":"16.26444440","name":"Asoumani"},{"id":"346674","latitude":"-2.29777780","longitude":"14.45583330","name":"Assala"},{"id":"346677","latitude":"-1.70444440","longitude":"15.97055560","name":"Assene"},{"id":"346678","latitude":"-1.02027780","longitude":"15.39972220","name":"Assengu\u00e9"},{"id":"346681","latitude":"-1.47472220","longitude":"15.60388890","name":"Assina"},{"id":"346686","latitude":"-1.58472220","longitude":"16.26444440","name":"Assoumani"},{"id":"346690","latitude":"-2.27583330","longitude":"14.54638890","name":"Atali"},{"id":"346696","latitude":"-1.29777780","longitude":"15.61861110","name":"Ati-Ati"},{"id":"346707","latitude":"-2.17166670","longitude":"15.49527780","name":"Babinga"},{"id":"346736","latitude":"-1.46277780","longitude":"15.56361110","name":"Balanganba"},{"id":"346737","latitude":"-2.36277780","longitude":"16.11972220","name":"Bal\u00e9mon"},{"id":"346740","latitude":"-1.30611110","longitude":"15.42416670","name":"Bali"},{"id":"346741","latitude":"-2.40000000","longitude":"16.01666670","name":"Balimo"},{"id":"346753","latitude":"-1.92000000","longitude":"15.84472220","name":"Bamba"},{"id":"346762","latitude":"-1.63305560","longitude":"15.92583330","name":"Bambou"},{"id":"346777","latitude":"-1.48444440","longitude":"16.18388890","name":"Bandja"},{"id":"346778","latitude":"-1.48444440","longitude":"16.18388890","name":"Bandjia"},{"id":"346784","latitude":"-1.01472220","longitude":"15.68972220","name":"Bandza"},{"id":"346790","latitude":"-2.44333330","longitude":"14.50444440","name":"Bandzi\u00e9m\u00e9"},{"id":"346793","latitude":"-2.43861110","longitude":"14.49166670","name":"Bandzounou"},{"id":"346797","latitude":"-1.58194440","longitude":"15.97972220","name":"Bangasou"},{"id":"346798","latitude":"-1.58194440","longitude":"15.97972220","name":"Bangassou"},{"id":"346808","latitude":"-1.16944440","longitude":"15.62805560","name":"Bangou\u00e9n\u00e9"},{"id":"346813","latitude":"-1.16944440","longitude":"15.62805560","name":"Bangw\u00e9n\u00e9"},{"id":"346819","latitude":"-1.81250000","longitude":"16.39916670","name":"Bants\u00e9"},{"id":"346859","latitude":"-1.67027780","longitude":"15.80166670","name":"Baya"},{"id":"346864","latitude":"-1.50833330","longitude":"15.08972220","name":"B\u00e9aba"},{"id":"346866","latitude":"-1.99555560","longitude":"15.13722220","name":"B\u00e9antsion"},{"id":"346868","latitude":"-1.69250000","longitude":"15.68638890","name":"Be\u00e9mpo"},{"id":"346869","latitude":"-2.06666670","longitude":"15.06666670","name":"B\u00e9hentsio"},{"id":"346871","latitude":"-1.43833330","longitude":"15.93472220","name":"B\u00e9kanga"},{"id":"346872","latitude":"-1.43833330","longitude":"15.93472220","name":"B\u00e9kanga I"},{"id":"346873","latitude":"-1.47055560","longitude":"15.90611110","name":"B\u00e9kanga II"},{"id":"346879","latitude":"-2.32694440","longitude":"14.57055560","name":"B\u00e9l\u00e9"},{"id":"346890","latitude":"-1.69250000","longitude":"15.68638890","name":"Bempo"},{"id":"346898","latitude":"-1.38722220","longitude":"15.93916670","name":"B\u00e9ne"},{"id":"346899","latitude":"-1.58333330","longitude":"15.99000000","name":"Beng\u00e9ko"},{"id":"346901","latitude":"-1.81250000","longitude":"16.39916670","name":"Bentz\u00e9"},{"id":"346909","latitude":"-2.48722220","longitude":"15.75555560","name":"Bessala"},{"id":"346985","latitude":"-2.45722220","longitude":"15.75916670","name":"Bio"},{"id":"346988","latitude":"-2.45722220","longitude":"15.75916670","name":"Biokono"},{"id":"347031","latitude":"-1.73694440","longitude":"14.98722220","name":"Bli"},{"id":"347033","latitude":"-1.36805560","longitude":"15.19361110","name":"Boa"},{"id":"347036","latitude":"-1.75555560","longitude":"16.33944440","name":"Bobana"},{"id":"347037","latitude":"-1.78944440","longitude":"16.31361110","name":"Bobanda"},{"id":"347040","latitude":"-1.61055560","longitude":"15.94805560","name":"Bobi"},{"id":"347045","latitude":"-1.63888890","longitude":"16.57166670","name":"Boby"},{"id":"347047","latitude":"-1.77305560","longitude":"16.44972220","name":"Bodouango"},{"id":"347048","latitude":"-1.75027780","longitude":"16.45361110","name":"Bodouango II"},{"id":"347049","latitude":"-1.72138890","longitude":"16.43916670","name":"Bodouango III"},{"id":"347050","latitude":"-1.77305560","longitude":"16.44972220","name":"Bodouongo"},{"id":"347052","latitude":"-1.70722220","longitude":"16.46694440","name":"Bodz\u00e9ka"},{"id":"347054","latitude":"-2.91555560","longitude":"15.63583330","name":"Bo\u00e9mb\u00e9"},{"id":"347061","latitude":"-2.52194440","longitude":"16.16611110","name":"Boilanga"},{"id":"347064","latitude":"-1.36805560","longitude":"15.19361110","name":"Boka"},{"id":"347092","latitude":"-1.60611110","longitude":"16.43638890","name":"Bokouanbolo"},{"id":"347116","latitude":"-1.69833330","longitude":"16.42944440","name":"Bombala"},{"id":"347170","latitude":"-1.69361110","longitude":"16.45555560","name":"Bosomba"},{"id":"347173","latitude":"-2.48722220","longitude":"15.75555560","name":"Bossala"},{"id":"347176","latitude":"-1.66666670","longitude":"16.20000000","name":"Boss\u00e9r\u00e9"},{"id":"347209","latitude":"-2.91666670","longitude":"15.58333330","name":"Bouamb\u00e9"},{"id":"347210","latitude":"-2.10166670","longitude":"16.16694440","name":"Bouanga"},{"id":"347218","latitude":"-1.52500000","longitude":"15.34472220","name":"Boub\u00e9"},{"id":"347220","latitude":"-1.40722220","longitude":"15.80194440","name":"Boubou"},{"id":"347235","latitude":"-2.16777780","longitude":"16.14083330","name":"Bouemba"},{"id":"347236","latitude":"-2.91555560","longitude":"15.63583330","name":"Bouemb\u00e9"},{"id":"347264","latitude":"-2.52194440","longitude":"16.16611110","name":"Boulanga"},{"id":"347265","latitude":"-2.32166670","longitude":"14.50166670","name":"Boulania"},{"id":"347271","latitude":"-1.68333330","longitude":"15.98333330","name":"Boulemo"},{"id":"347276","latitude":"-1.95000000","longitude":"16.31666670","name":"Bouloka"},{"id":"347280","latitude":"-1.43305560","longitude":"15.95361110","name":"Boulou"},{"id":"347286","latitude":"-1.44750000","longitude":"15.87638890","name":"Bouma"},{"id":"347291","latitude":"-1.54722220","longitude":"16.09055560","name":"Boumba"},{"id":"347296","latitude":"-1.44750000","longitude":"15.87638890","name":"Boume"},{"id":"347299","latitude":"-1.58833330","longitude":"16.57666670","name":"Bounda"},{"id":"347304","latitude":"-1.61666670","longitude":"16.30000000","name":"Boundji"},{"id":"347312","latitude":"-1.00166670","longitude":"15.44416670","name":"Bounga"},{"id":"347361","latitude":"-2.82000000","longitude":"16.18361110","name":"Bowando"},{"id":"347369","latitude":"-1.86194440","longitude":"16.33583330","name":"Boy\u00e9y\u00e9"},{"id":"347379","latitude":"-1.65944440","longitude":"15.28361110","name":"Bvi"},{"id":"347380","latitude":"-1.65944440","longitude":"15.28361110","name":"Bvie"},{"id":"347382","latitude":"-2.91555560","longitude":"15.63583330","name":"Bwanb\u00e9"},{"id":"347383","latitude":"-2.52194440","longitude":"16.16611110","name":"Bwanlanga"},{"id":"347384","latitude":"-2.16777780","longitude":"16.14083330","name":"Bwemba"},{"id":"347402","latitude":"-1.22416670","longitude":"15.95916670","name":"Como"},{"id":"347418","latitude":"-2.54472220","longitude":"14.75333330","name":"Dambala"},{"id":"347431","latitude":"-2.07916670","longitude":"16.18583330","name":"Dendaba"},{"id":"347472","latitude":"-1.14527780","longitude":"15.84833330","name":"Dimi"},{"id":"347475","latitude":"-1.92416670","longitude":"16.31388890","name":"Dimou"},{"id":"347476","latitude":"-1.32638890","longitude":"16.21861110","name":"Dinda"},{"id":"347504","latitude":"-2.54472220","longitude":"14.75333330","name":"Djambala"},{"id":"347505","latitude":"-2.54472220","longitude":"14.75333330","name":"Djamballa"},{"id":"347507","latitude":"-2.39638890","longitude":"14.48444440","name":"Djanbala"},{"id":"347509","latitude":"-2.11361110","longitude":"14.64305560","name":"Djani"},{"id":"347523","latitude":"-2.09611110","longitude":"15.60444440","name":"Djoabouri"},{"id":"347536","latitude":"-1.40722220","longitude":"15.94194440","name":"Djou"},{"id":"347539","latitude":"-1.87055560","longitude":"15.90833330","name":"Djouo"},{"id":"347551","latitude":"-1.28861110","longitude":"16.11805560","name":"Dongo"},{"id":"347552","latitude":"-1.37944440","longitude":"15.82250000","name":"Dongo-Mok\u00e9"},{"id":"347598","latitude":"-1.95638890","longitude":"16.18555560","name":"Dzabi"},{"id":"347608","latitude":"-2.11361110","longitude":"14.64305560","name":"Dzani"},{"id":"347629","latitude":"-1.52750000","longitude":"15.00527780","name":"Dzogo II"},{"id":"347632","latitude":"-1.90472220","longitude":"16.29666670","name":"Dzolokonzo"},{"id":"347640","latitude":"-2.26333330","longitude":"15.00555560","name":"Ebaba"},{"id":"347641","latitude":"-1.21972220","longitude":"15.78277780","name":"Eba"},{"id":"347644","latitude":"-2.26333330","longitude":"15.00555560","name":"Ebala"},{"id":"347653","latitude":"-1.76194440","longitude":"14.98555560","name":"Ebani"},{"id":"347660","latitude":"-1.55055560","longitude":"15.68333330","name":"Ebiamboma"},{"id":"347661","latitude":"-2.54527780","longitude":"16.17583330","name":"Ebi"},{"id":"347662","latitude":"-1.69194440","longitude":"16.06083330","name":"Ebi\u00e9s\u00e9"},{"id":"347668","latitude":"-1.23611110","longitude":"15.62138890","name":"Ebongo"},{"id":"347672","latitude":"-1.91333330","longitude":"14.83944440","name":"Ebono"},{"id":"347673","latitude":"-1.70472220","longitude":"16.27638890","name":"Ebonton"},{"id":"347674","latitude":"-1.28888890","longitude":"15.87527780","name":"Eboro"},{"id":"347678","latitude":"-1.28333330","longitude":"15.58694440","name":"Ebou"},{"id":"347679","latitude":"-1.86666670","longitude":"16.03333330","name":"Ebouie"},{"id":"347680","latitude":"-1.60638890","longitude":"16.35388890","name":"Ebouli"},{"id":"347685","latitude":"-1.91333330","longitude":"14.83944440","name":"Ebouo"},{"id":"347686","latitude":"-1.13388890","longitude":"15.60972220","name":"Eboyo"},{"id":"347687","latitude":"-2.21027780","longitude":"15.03500000","name":"Ebva"},{"id":"347688","latitude":"-1.40916670","longitude":"15.41555560","name":"Ebvoura"},{"id":"347698","latitude":"-2.53416670","longitude":"14.68805560","name":"Edz\u00e9o"},{"id":"347699","latitude":"-2.32333330","longitude":"14.48305560","name":"Edzouans\u00e9k\u00e9"},{"id":"347701","latitude":"-1.50611110","longitude":"15.86500000","name":"Edzoumou"},{"id":"347702","latitude":"-1.50611110","longitude":"15.86500000","name":"Edzounou"},{"id":"347703","latitude":"-1.75000000","longitude":"16.23333330","name":"E\u00e9r\u00e9"},{"id":"347704","latitude":"-1.60055560","longitude":"15.97888890","name":"Efoundou"},{"id":"347705","latitude":"-2.18916670","longitude":"15.04333330","name":"Egali"},{"id":"347713","latitude":"-1.28388890","longitude":"15.44555560","name":"Ekaga"},{"id":"347719","latitude":"-1.42250000","longitude":"15.69194440","name":"Ekari"},{"id":"347720","latitude":"-1.46444440","longitude":"15.82138890","name":"Ekasa"},{"id":"347722","latitude":"-1.44361110","longitude":"15.94111110","name":"Ekassa"},{"id":"347725","latitude":"-2.34305560","longitude":"14.48916670","name":"Ek\u00e9l\u00e9"},{"id":"347730","latitude":"-1.48305560","longitude":"15.87027780","name":"Eki\u00e9"},{"id":"347735","latitude":"-1.28388890","longitude":"15.44555560","name":"Eko"},{"id":"347738","latitude":"-1.08722220","longitude":"15.62611110","name":"Ekolo"},{"id":"347746","latitude":"-1.45222220","longitude":"16.32000000","name":"Ekongo"},{"id":"347749","latitude":"-2.15361110","longitude":"15.50250000","name":"Ekorokoro"},{"id":"347750","latitude":"-1.29222220","longitude":"15.87472220","name":"Ekoso"},{"id":"347755","latitude":"-1.17000000","longitude":"15.71916670","name":"Ekouassend\u00e9"},{"id":"347758","latitude":"-1.26083330","longitude":"16.02194440","name":"Ekouili"},{"id":"347765","latitude":"-1.18194440","longitude":"15.87138890","name":"Ekoungou"},{"id":"347771","latitude":"-1.17000000","longitude":"15.71916670","name":"Ekwasend\u00e9"},{"id":"347772","latitude":"-1.16361110","longitude":"15.76861110","name":"Ekwasend\u00e9-Mok\u00e9"},{"id":"347780","latitude":"-1.55611110","longitude":"15.43916670","name":"Eli\u00e9li\u00e9"},{"id":"347781","latitude":"-1.55611110","longitude":"15.43916670","name":"Elieli"},{"id":"347786","latitude":"-2.01666670","longitude":"15.87222220","name":"Elion"},{"id":"347791","latitude":"-1.54138890","longitude":"16.04472220","name":"Elo"},{"id":"347793","latitude":"-1.54138890","longitude":"16.04472220","name":"Elo I"},{"id":"347794","latitude":"-1.54972220","longitude":"16.05361110","name":"Elo II"},{"id":"347795","latitude":"-1.54555560","longitude":"16.06055560","name":"Elo III"},{"id":"347796","latitude":"-1.40388890","longitude":"15.61555560","name":"Elolo"},{"id":"347798","latitude":"-1.42138890","longitude":"15.77666670","name":"Elondi"},{"id":"347799","latitude":"-1.44222220","longitude":"15.96277780","name":"Elonga"},{"id":"347800","latitude":"-1.46805560","longitude":"15.98583330","name":"Elonga I"},{"id":"347801","latitude":"-1.44222220","longitude":"15.96277780","name":"Elonga II"},{"id":"347804","latitude":"-1.42138890","longitude":"15.77666670","name":"Eloudi"},{"id":"347805","latitude":"-2.48944440","longitude":"15.89055560","name":"Elouna"},{"id":"347806","latitude":"-1.57694440","longitude":"16.32722220","name":"Eloundi"},{"id":"347809","latitude":"-1.75972220","longitude":"15.99388890","name":"Elouo"},{"id":"347810","latitude":"-1.74444440","longitude":"15.98111110","name":"Elouongouala"},{"id":"347811","latitude":"-1.74444440","longitude":"15.98111110","name":"Elouongwala"},{"id":"347814","latitude":"-2.01861110","longitude":"15.71750000","name":"Embama"},{"id":"347815","latitude":"-1.35555560","longitude":"15.60027780","name":"Emb\u00e9n\u00e9"},{"id":"347816","latitude":"-1.35555560","longitude":"15.60027780","name":"Embeni"},{"id":"347819","latitude":"-1.26305560","longitude":"15.46166670","name":"Embouli"},{"id":"347820","latitude":"-2.41361110","longitude":"14.58000000","name":"Embouma"},{"id":"347821","latitude":"-1.82416670","longitude":"15.20888890","name":"Embouon"},{"id":"347822","latitude":"-2.42361110","longitude":"14.46888890","name":"Emonpibi"},{"id":"347823","latitude":"-2.72916670","longitude":"15.26972220","name":"Emp\u00e9"},{"id":"347824","latitude":"-2.72916670","longitude":"15.26972220","name":"Empe\u00ef"},{"id":"347830","latitude":"-1.31333330","longitude":"15.73250000","name":"Endoulou"},{"id":"347832","latitude":"-2.05194440","longitude":"15.64666670","name":"Eneinkw\u00e9r\u00e9"},{"id":"347834","latitude":"-2.18916670","longitude":"15.04333330","name":"Engali"},{"id":"347837","latitude":"-1.14111110","longitude":"15.79861110","name":"Enganga"},{"id":"347838","latitude":"-2.18194440","longitude":"15.86111110","name":"Engankou"},{"id":"347839","latitude":"-1.52277780","longitude":"15.40194440","name":"Engi\u00e9"},{"id":"347844","latitude":"-1.76277780","longitude":"15.93777780","name":"Engou\u00e9l\u00e9"},{"id":"347846","latitude":"-1.85750000","longitude":"15.28416670","name":"Engouma"},{"id":"347847","latitude":"-1.56388890","longitude":"15.88694440","name":"Eniangamba"},{"id":"347850","latitude":"-1.77666670","longitude":"15.80222220","name":"Enkandziana I"},{"id":"347851","latitude":"-1.67444440","longitude":"15.64916670","name":"Enkandziana II"},{"id":"347852","latitude":"-1.67444440","longitude":"15.64916670","name":"Enkatsiana"},{"id":"347855","latitude":"-2.31833330","longitude":"14.51722220","name":"Enkouara"},{"id":"347856","latitude":"-2.34055560","longitude":"14.57111110","name":"Enkoulou"},{"id":"347857","latitude":"-1.75138890","longitude":"15.20777780","name":"Enta"},{"id":"347858","latitude":"-2.23972220","longitude":"15.01972220","name":"Entou"},{"id":"347859","latitude":"-1.40416670","longitude":"15.31388890","name":"Ents\u00e9l\u00e9"},{"id":"347861","latitude":"-1.36555560","longitude":"15.56500000","name":"Entsi\u00e9l\u00e9"},{"id":"347862","latitude":"-1.39194440","longitude":"15.61277780","name":"Entsi\u00e9l\u00e9-Mok\u00e9"},{"id":"347867","latitude":"-1.03638890","longitude":"15.71611110","name":"Eouassi"},{"id":"347870","latitude":"-1.22777780","longitude":"15.99083330","name":"Epa"},{"id":"347874","latitude":"-2.47444440","longitude":"14.81861110","name":"Epari"},{"id":"347879","latitude":"-2.77833330","longitude":"15.33944440","name":"Epinantsa"},{"id":"347880","latitude":"-2.77833330","longitude":"15.33944440","name":"Epinatsa"},{"id":"347881","latitude":"-1.37416670","longitude":"16.02472220","name":"Eping\u00e9"},{"id":"347885","latitude":"-1.09861110","longitude":"15.60722220","name":"Epou"},{"id":"347886","latitude":"-1.16638890","longitude":"15.87138890","name":"Epougnou"},{"id":"347887","latitude":"-1.09861110","longitude":"15.60722220","name":"Epouho"},{"id":"347888","latitude":"-1.51055560","longitude":"15.90000000","name":"Epoumou"},{"id":"347889","latitude":"-1.42944440","longitude":"15.70916670","name":"Epoundou"},{"id":"347890","latitude":"-1.16638890","longitude":"15.87138890","name":"Epounou"},{"id":"347891","latitude":"-2.33333330","longitude":"14.62027780","name":"Esagi"},{"id":"347892","latitude":"-2.31250000","longitude":"14.67333330","name":"Esala"},{"id":"347893","latitude":"-2.20666670","longitude":"14.60583330","name":"Esami"},{"id":"347894","latitude":"-2.43333330","longitude":"15.29361110","name":"Esan"},{"id":"347895","latitude":"-1.01111110","longitude":"15.73388890","name":"Esanga"},{"id":"347898","latitude":"-1.49722220","longitude":"15.86555560","name":"Esiala"},{"id":"347899","latitude":"-2.13027780","longitude":"15.53500000","name":"Esial"},{"id":"347900","latitude":"-1.40527780","longitude":"16.06861110","name":"Esibili"},{"id":"347901","latitude":"-1.45361110","longitude":"15.60583330","name":"Esi"},{"id":"347906","latitude":"-2.31250000","longitude":"14.67333330","name":"Essala"},{"id":"347907","latitude":"-1.49722220","longitude":"15.86555560","name":"Essiala"},{"id":"347908","latitude":"-1.40527780","longitude":"16.06861110","name":"Essibili"},{"id":"347918","latitude":"-1.88333330","longitude":"15.85000000","name":"Etaba"},{"id":"347921","latitude":"-1.33333330","longitude":"16.01666670","name":"Etandi"},{"id":"347927","latitude":"-2.47444440","longitude":"15.79222220","name":"Eti\u00e9me"},{"id":"347928","latitude":"-2.47444440","longitude":"15.79222220","name":"Eti\u00e9n\u00e9"},{"id":"347931","latitude":"-2.38361110","longitude":"14.57250000","name":"Etogo Tsami"},{"id":"347933","latitude":"-1.55000000","longitude":"15.66638890","name":"Etolo"},{"id":"347935","latitude":"-1.39805560","longitude":"16.05472220","name":"Etono"},{"id":"347936","latitude":"-1.70472220","longitude":"16.27638890","name":"Etonton"},{"id":"347937","latitude":"-1.41750000","longitude":"15.99777780","name":"Etoro"},{"id":"347938","latitude":"-1.66472220","longitude":"15.99416670","name":"Etoro II"},{"id":"347942","latitude":"-1.75305560","longitude":"15.48388890","name":"Etsi"},{"id":"347943","latitude":"-2.85666670","longitude":"15.55861110","name":"Etsouali"},{"id":"347944","latitude":"-2.51000000","longitude":"15.01472220","name":"Etzou\u00e9s\u00e9"},{"id":"347945","latitude":"-2.21027780","longitude":"15.03500000","name":"Eva"},{"id":"347946","latitude":"-1.03638890","longitude":"15.71611110","name":"Ewasi"},{"id":"347951","latitude":"-1.44527780","longitude":"15.56416670","name":"Eyoulou"},{"id":"347957","latitude":"-1.53222220","longitude":"15.88416670","name":"Foba"},{"id":"347958","latitude":"-1.53222220","longitude":"15.88416670","name":"Fobo"},{"id":"347984","latitude":"-1.43500000","longitude":"16.06888890","name":"Gagnia"},{"id":"347985","latitude":"-1.72638890","longitude":"15.91416670","name":"Gaki\u00e9l\u00e9"},{"id":"347986","latitude":"-2.28722220","longitude":"14.48388890","name":"Gakili"},{"id":"347994","latitude":"-1.57638890","longitude":"15.91972220","name":"Gamba"},{"id":"347996","latitude":"-2.43861110","longitude":"14.44666670","name":"Gambi\u00e9"},{"id":"347998","latitude":"-1.31694440","longitude":"15.20333330","name":"Gambo"},{"id":"347999","latitude":"-1.31694440","longitude":"15.20333330","name":"Gambogo"},{"id":"348000","latitude":"-1.87638890","longitude":"15.86444440","name":"Gamboma"},{"id":"348012","latitude":"-1.23444440","longitude":"15.99583330","name":"Ganba"},{"id":"348013","latitude":"-2.43861110","longitude":"14.44666670","name":"Ganbi\u00e9"},{"id":"348030","latitude":"-1.33277780","longitude":"15.89527780","name":"Gania"},{"id":"348031","latitude":"-1.72638890","longitude":"15.91416670","name":"Ganki\u00e9l\u00e9"},{"id":"348032","latitude":"-1.43388890","longitude":"15.27277780","name":"Gankoma"},{"id":"348033","latitude":"-2.34944440","longitude":"14.49055560","name":"Gankou"},{"id":"348035","latitude":"-1.44111110","longitude":"15.26000000","name":"Gantala"},{"id":"348039","latitude":"-2.54888890","longitude":"16.03583330","name":"Gantsanki\u00e9"},{"id":"348040","latitude":"-2.54888890","longitude":"16.03583330","name":"Gantsink\u00e9"},{"id":"348048","latitude":"-2.53333330","longitude":"16.16666670","name":"Gayikay"},{"id":"348049","latitude":"-1.46444440","longitude":"15.77388890","name":"G\u00e9l\u00e9-Okasa"},{"id":"348050","latitude":"-1.41500000","longitude":"15.30666670","name":"Gelibi"},{"id":"348054","latitude":"-1.64444440","longitude":"15.96166670","name":"Gien"},{"id":"348061","latitude":"-1.83861110","longitude":"15.83916670","name":"Goban"},{"id":"348083","latitude":"-1.35055560","longitude":"15.96694440","name":"Gosi-Gosi"},{"id":"348084","latitude":"-1.35055560","longitude":"15.96694440","name":"Gossi Gossi"},{"id":"348091","latitude":"-2.35000000","longitude":"15.96666670","name":"Gou\u00e9nd\u00e9"},{"id":"348092","latitude":"-1.36638890","longitude":"15.90500000","name":"Gou\u00e9n\u00e9"},{"id":"348095","latitude":"-1.67305560","longitude":"15.95694440","name":"Goui"},{"id":"348096","latitude":"-2.40972220","longitude":"14.50194440","name":"Goulanbali"},{"id":"348097","latitude":"-1.81888890","longitude":"16.02472220","name":"Goulangampina"},{"id":"348098","latitude":"-1.81888890","longitude":"16.02472220","name":"Goulanganpini"},{"id":"348099","latitude":"-2.45111110","longitude":"14.41277780","name":"Goulanpika"},{"id":"348103","latitude":"-2.41722220","longitude":"14.58472220","name":"Goulonkila"},{"id":"348109","latitude":"-2.19222220","longitude":"15.47222220","name":"Gounantsio"},{"id":"348110","latitude":"-2.19222220","longitude":"15.47222220","name":"Gounatsio"},{"id":"348119","latitude":"-2.45111110","longitude":"14.41277780","name":"Goutanpika"},{"id":"348122","latitude":"-1.45444440","longitude":"15.96138890","name":"Gu\u00e9la-Como"},{"id":"348124","latitude":"-1.36305560","longitude":"15.99694440","name":"Gu\u00e9l\u00e9"},{"id":"348125","latitude":"-1.46444440","longitude":"15.77388890","name":"Guel\u00e9-Okassa"},{"id":"348129","latitude":"-1.79694440","longitude":"16.42555560","name":"Guiabombo"},{"id":"348132","latitude":"-2.20388890","longitude":"14.50444440","name":"Guipini"},{"id":"348134","latitude":"-1.36638890","longitude":"15.90500000","name":"Gw\u00e9n\u00e9"},{"id":"348147","latitude":"-1.42805560","longitude":"16.30833330","name":"Ibabi"},{"id":"348150","latitude":"-2.26333330","longitude":"15.00555560","name":"Iballa"},{"id":"348155","latitude":"-2.90444440","longitude":"16.16500000","name":"Ib\u00e9"},{"id":"348163","latitude":"-1.69194440","longitude":"16.06083330","name":"Ibiesse"},{"id":"348164","latitude":"-1.37777780","longitude":"15.84472220","name":"Ibinda"},{"id":"348166","latitude":"-1.35861110","longitude":"15.54111110","name":"Iboboli"},{"id":"348175","latitude":"-1.19805560","longitude":"15.51305560","name":"Ibounga"},{"id":"348212","latitude":"-1.76722220","longitude":"15.25083330","name":"Iko"},{"id":"348224","latitude":"-1.26083330","longitude":"16.02194440","name":"Ikou\u00e9l\u00e9"},{"id":"348238","latitude":"-2.70388890","longitude":"16.19583330","name":"Ilanga"},{"id":"348260","latitude":"-2.01861110","longitude":"15.71750000","name":"Imbana"},{"id":"348264","latitude":"-1.78444440","longitude":"15.80611110","name":"Imbou"},{"id":"348268","latitude":"-2.66250000","longitude":"15.39388890","name":"Imbouri"},{"id":"348274","latitude":"-2.72916670","longitude":"15.26972220","name":"Impe"},{"id":"348278","latitude":"-1.56222220","longitude":"15.88722220","name":"Impini"},{"id":"348280","latitude":"-2.50361110","longitude":"15.16805560","name":"Impo"},{"id":"348283","latitude":"-1.63305560","longitude":"15.88583330","name":"Imporo"},{"id":"348293","latitude":"-1.48694440","longitude":"16.01750000","name":"Indoulou"},{"id":"348297","latitude":"-1.55000000","longitude":"15.99638890","name":"Indzie"},{"id":"348302","latitude":"-1.51138890","longitude":"15.79972220","name":"Inga"},{"id":"348304","latitude":"-2.18194440","longitude":"15.86111110","name":"Ingakou"},{"id":"348307","latitude":"-1.59388890","longitude":"16.04388890","name":"Ingana"},{"id":"348309","latitude":"-2.50583330","longitude":"14.70750000","name":"Ingangouon"},{"id":"348312","latitude":"-1.64444440","longitude":"15.96166670","name":"Ingien"},{"id":"348313","latitude":"-2.17833330","longitude":"15.05361110","name":"Ingoini-Mok\u00e9"},{"id":"348319","latitude":"-2.17833330","longitude":"15.05361110","name":"Ingouani"},{"id":"348321","latitude":"-1.88583330","longitude":"16.14805560","name":"Ingou\u00e9l\u00e9"},{"id":"348323","latitude":"-1.73861110","longitude":"16.11194440","name":"Ingou\u00e9n\u00e9"},{"id":"348324","latitude":"-1.88833330","longitude":"16.12611110","name":"Ingou"},{"id":"348327","latitude":"-2.50000000","longitude":"15.01611110","name":"Ingouna"},{"id":"348329","latitude":"-2.17833330","longitude":"15.05361110","name":"Ingouoni-Mok\u00e9"},{"id":"348334","latitude":"-1.59388890","longitude":"16.04388890","name":"Inguina"},{"id":"348336","latitude":"-1.76277780","longitude":"15.93777780","name":"Ingw\u00e9n\u00e9"},{"id":"348339","latitude":"-1.97611110","longitude":"15.77416670","name":"Inka"},{"id":"348342","latitude":"-1.68333330","longitude":"16.11083330","name":"Inkan"},{"id":"348350","latitude":"-2.45472220","longitude":"14.51222220","name":"Inkouara"},{"id":"348353","latitude":"-1.59861110","longitude":"15.87416670","name":"Inkou\u00e9l\u00e9"},{"id":"348354","latitude":"-1.59861110","longitude":"15.87416670","name":"Inkou\u00e9ri"},{"id":"348356","latitude":"-1.59861110","longitude":"15.87416670","name":"Inkouli"},{"id":"348358","latitude":"-1.77277780","longitude":"15.87250000","name":"Inkousou"},{"id":"348359","latitude":"-1.77277780","longitude":"15.87250000","name":"Inkoussou"},{"id":"348366","latitude":"-1.56222220","longitude":"15.88722220","name":"Inpini"},{"id":"348367","latitude":"-1.69555560","longitude":"15.97888890","name":"Inpw\u00e9n\u00e9"},{"id":"348368","latitude":"-2.54388890","longitude":"15.10083330","name":"Insa"},{"id":"348369","latitude":"-1.99388890","longitude":"16.14472220","name":"Insianva"},{"id":"348372","latitude":"-1.75138890","longitude":"15.20777780","name":"Inta"},{"id":"348373","latitude":"-1.88333330","longitude":"16.03333330","name":"Intala"},{"id":"348375","latitude":"-1.69138890","longitude":"16.04750000","name":"Int\u00e9s\u00e9"},{"id":"348377","latitude":"-2.27500000","longitude":"15.43666670","name":"Intou II"},{"id":"348378","latitude":"-2.29361110","longitude":"15.43194440","name":"Intou I"},{"id":"348379","latitude":"-1.71083330","longitude":"16.10055560","name":"Intsiala"},{"id":"348380","latitude":"-2.06500000","longitude":"15.89388890","name":"Intsi\u00e9l\u00e9"},{"id":"348381","latitude":"-1.97222220","longitude":"15.77916670","name":"Invoua"},{"id":"348395","latitude":"-2.77166670","longitude":"15.35750000","name":"Isala"},{"id":"348397","latitude":"-1.40638890","longitude":"16.19472220","name":"Isemba"},{"id":"348400","latitude":"-1.98222220","longitude":"15.75527780","name":"Isiolo"},{"id":"348423","latitude":"-1.52611110","longitude":"15.89833330","name":"Ito"},{"id":"348426","latitude":"-1.27166670","longitude":"15.65194440","name":"Itoumba"},{"id":"348431","latitude":"-2.67666670","longitude":"15.29666670","name":"Itzou\u00e9s\u00e9"},{"id":"348442","latitude":"-1.28861110","longitude":"16.11805560","name":"Kaba"},{"id":"348453","latitude":"-1.62027780","longitude":"15.00722220","name":"Kadjouni"},{"id":"348466","latitude":"-1.48361110","longitude":"16.16055560","name":"Kalanga"},{"id":"348479","latitude":"-1.31638890","longitude":"15.55222220","name":"Kana"},{"id":"348492","latitude":"-1.97361110","longitude":"16.28916670","name":"Kangakanga"},{"id":"348502","latitude":"-2.41472220","longitude":"14.43500000","name":"Kangouono"},{"id":"348505","latitude":"-1.33583330","longitude":"15.76166670","name":"Kani"},{"id":"348508","latitude":"-2.31833330","longitude":"14.51722220","name":"Kankouara"},{"id":"348514","latitude":"-2.46000000","longitude":"14.90750000","name":"Kaon"},{"id":"348540","latitude":"-1.51722220","longitude":"15.93333330","name":"Kay\u00e9"},{"id":"348554","latitude":"-2.36444440","longitude":"14.54361110","name":"K\u00e9bala"},{"id":"348556","latitude":"-2.45027780","longitude":"14.42250000","name":"K\u00e9bara"},{"id":"348568","latitude":"-1.50916670","longitude":"15.52361110","name":"K\u00e9l\u00e9mi\u00e9"},{"id":"348570","latitude":"-1.50916670","longitude":"15.52361110","name":"Kelli\u00e9m\u00e9"},{"id":"348579","latitude":"-1.37694440","longitude":"15.41166670","name":"Kendouo"},{"id":"348583","latitude":"-2.37222220","longitude":"14.54666670","name":"Keng\u00e9l\u00e9"},{"id":"348585","latitude":"-1.54583330","longitude":"15.07250000","name":"Kengouani"},{"id":"348587","latitude":"-1.54583330","longitude":"15.07250000","name":"Kengwani"},{"id":"348602","latitude":"-2.43472220","longitude":"14.41027780","name":"Ketzoua"},{"id":"348606","latitude":"-1.99833330","longitude":"15.73777780","name":"Kiakouo"},{"id":"348607","latitude":"-2.53972220","longitude":"15.10138890","name":"Kial\u00e9"},{"id":"348609","latitude":"-2.39083330","longitude":"14.52222220","name":"Kiama"},{"id":"348867","latitude":"-2.38833330","longitude":"14.45500000","name":"Kingambini"},{"id":"348885","latitude":"-2.43250000","longitude":"14.41944440","name":"Kingolo"},{"id":"348906","latitude":"-1.54583330","longitude":"15.07250000","name":"Kingouoni"},{"id":"349047","latitude":"-1.62222220","longitude":"15.52805560","name":"Kiri"},{"id":"349128","latitude":"-1.22416670","longitude":"15.95916670","name":"Komo"},{"id":"349139","latitude":"-1.07638890","longitude":"15.74250000","name":"Kongalikou"},{"id":"349144","latitude":"-1.67250000","longitude":"16.45222220","name":"Kongo"},{"id":"349149","latitude":"-1.00472220","longitude":"15.56166670","name":"Koni-Koni"},{"id":"349156","latitude":"-1.23416670","longitude":"15.68000000","name":"Kosouna"},{"id":"349157","latitude":"-1.25500000","longitude":"15.67388890","name":"Kossouna"},{"id":"349164","latitude":"-1.78361110","longitude":"15.35055560","name":"Kouai"},{"id":"349186","latitude":"-1.65777780","longitude":"15.30611110","name":"Kou\u00e9"},{"id":"349223","latitude":"-2.23000000","longitude":"15.46888890","name":"Koumou"},{"id":"349236","latitude":"-1.54111110","longitude":"16.39972220","name":"Kounga"},{"id":"349245","latitude":"-2.44861110","longitude":"14.43083330","name":"Kouni"},{"id":"349263","latitude":"-1.82138890","longitude":"14.88250000","name":"Kouti"},{"id":"349285","latitude":"-1.22916670","longitude":"15.67916670","name":"Langalanga"},{"id":"349296","latitude":"-1.15750000","longitude":"15.44694440","name":"L\u00e9bala"},{"id":"349300","latitude":"-1.32833330","longitude":"15.82388890","name":"Lebangui"},{"id":"349313","latitude":"-1.74694440","longitude":"16.11416670","name":"L\u00e9bou"},{"id":"349316","latitude":"-2.32527780","longitude":"14.60000000","name":"Lecania"},{"id":"349321","latitude":"-2.91666670","longitude":"15.65000000","name":"L\u00e9fini"},{"id":"349322","latitude":"-2.93250000","longitude":"16.16305560","name":"Lefinimpala"},{"id":"349323","latitude":"-1.95833330","longitude":"15.99805560","name":"L\u00e9foumou"},{"id":"349324","latitude":"-1.95833330","longitude":"15.99805560","name":"L\u00e9founou"},{"id":"349325","latitude":"-1.95583330","longitude":"15.02333330","name":"Lefourou"},{"id":"349330","latitude":"-1.74000000","longitude":"16.01416670","name":"L\u00e9kana"},{"id":"349333","latitude":"-2.32527780","longitude":"14.60000000","name":"Lekania"},{"id":"349340","latitude":"-1.59333330","longitude":"14.95555560","name":"L\u00e9k\u00e9ti"},{"id":"349341","latitude":"-1.59333330","longitude":"14.95555560","name":"Lekety"},{"id":"349342","latitude":"-1.59333330","longitude":"14.95555560","name":"L\u00e9kita"},{"id":"349345","latitude":"-1.93333330","longitude":"16.28333330","name":"Lekondji"},{"id":"349348","latitude":"-1.08222220","longitude":"15.58138890","name":"L\u00e9kouala"},{"id":"349351","latitude":"-1.68055560","longitude":"15.51555560","name":"Lekwon"},{"id":"349375","latitude":"-1.62472220","longitude":"16.08527780","name":"Lesanga"},{"id":"349378","latitude":"-1.56888890","longitude":"15.72111110","name":"L\u00e9sia"},{"id":"349379","latitude":"-1.71444440","longitude":"15.95666670","name":"L\u00e9sia-Tsounou"},{"id":"349380","latitude":"-1.61722220","longitude":"16.18555560","name":"Lessanga"},{"id":"349383","latitude":"-1.56888890","longitude":"15.72111110","name":"Lessia"},{"id":"349385","latitude":"-1.71444440","longitude":"15.95666670","name":"Lessia-Tson"},{"id":"349388","latitude":"-1.60222220","longitude":"15.76722220","name":"L\u00e9to"},{"id":"349408","latitude":"-1.84638890","longitude":"16.06555560","name":"Lien"},{"id":"349420","latitude":"-1.82444440","longitude":"14.88833330","name":"Likouala"},{"id":"349427","latitude":"-1.35277780","longitude":"15.50750000","name":"Lima"},{"id":"349428","latitude":"-1.35277780","longitude":"15.50750000","name":"Limo"},{"id":"349449","latitude":"-2.63027780","longitude":"16.21777780","name":"Lisalangomba"},{"id":"349469","latitude":"-1.04166670","longitude":"15.79222220","name":"Loemba"},{"id":"349474","latitude":"-1.85250000","longitude":"16.31916670","name":"Loko"},{"id":"349503","latitude":"-1.54972220","longitude":"15.61666670","name":"Loto"},{"id":"349610","latitude":"-2.08861110","longitude":"15.08500000","name":"M\u00e2a"},{"id":"349620","latitude":"-1.98333330","longitude":"14.95000000","name":"Mabaya"},{"id":"349631","latitude":"-1.04027780","longitude":"15.77666670","name":"Mabirou"},{"id":"349636","latitude":"-1.95000000","longitude":"15.41666670","name":"Maboko"},{"id":"349643","latitude":"-1.91388890","longitude":"16.31416670","name":"Maboua"},{"id":"349650","latitude":"-1.85916670","longitude":"16.36444440","name":"Mabwa"},{"id":"349673","latitude":"-1.51527780","longitude":"15.39277780","name":"Madzala"},{"id":"349700","latitude":"-2.08861110","longitude":"15.08500000","name":"Mah"},{"id":"349762","latitude":"-1.99527780","longitude":"16.31527780","name":"Makotimpoko"},{"id":"349763","latitude":"-1.99527780","longitude":"16.31527780","name":"Makotipoko"},{"id":"349767","latitude":"-1.98750000","longitude":"16.32222220","name":"Makouango"},{"id":"349826","latitude":"-2.08861110","longitude":"15.08500000","name":"Ma"},{"id":"349843","latitude":"-2.86555560","longitude":"16.16666670","name":"Mamp\u00e9"},{"id":"349901","latitude":"-2.40416670","longitude":"14.44388890","name":"Mang\u00e9l\u00e9"},{"id":"349918","latitude":"-2.51222220","longitude":"14.85361110","name":"Manianga"},{"id":"349963","latitude":"-1.51916670","longitude":"16.13722220","name":"Map\u00e9m\u00e9"},{"id":"349980","latitude":"-2.29777780","longitude":"14.45583330","name":"Masala"},{"id":"349982","latitude":"-1.92611110","longitude":"16.20666670","name":"Masali"},{"id":"350006","latitude":"-1.37583330","longitude":"16.18388890","name":"Massali"},{"id":"350119","latitude":"-2.30666670","longitude":"14.51777780","name":"Mayouka"},{"id":"350127","latitude":"-1.57611110","longitude":"15.78305560","name":"Mba\u00e9so"},{"id":"350139","latitude":"-2.33638890","longitude":"14.44027780","name":"Mbali"},{"id":"350148","latitude":"-1.27805560","longitude":"15.58222220","name":"Mba"},{"id":"350149","latitude":"-1.27805560","longitude":"15.58222220","name":"M'Ba"},{"id":"350157","latitude":"-2.07833330","longitude":"15.59888890","name":"Mbanba"},{"id":"350160","latitude":"-1.48444440","longitude":"16.18388890","name":"Mbandza"},{"id":"350164","latitude":"-1.74305560","longitude":"15.94805560","name":"Mban"},{"id":"350165","latitude":"-1.74305560","longitude":"15.94805560","name":"M'Ban"},{"id":"350167","latitude":"-1.81250000","longitude":"16.39916670","name":"Mbants\u00e9"},{"id":"350198","latitude":"-1.28861110","longitude":"15.61250000","name":"Mbaya"},{"id":"350210","latitude":"-1.60527780","longitude":"15.92666670","name":"Mb\u00e9"},{"id":"350248","latitude":"-1.54888890","longitude":"16.03583330","name":"Mbobo"},{"id":"350250","latitude":"-1.19111110","longitude":"15.42833330","name":"Mbogo"},{"id":"350251","latitude":"-1.19111110","longitude":"15.42833330","name":"M'Bogo"},{"id":"350253","latitude":"-1.81138890","longitude":"15.46944440","name":"Mboi"},{"id":"350261","latitude":"-1.61055560","longitude":"15.94805560","name":"Mboli"},{"id":"350262","latitude":"-1.61055560","longitude":"15.94805560","name":"M'Boli"},{"id":"350279","latitude":"-2.31222220","longitude":"14.62583330","name":"Mbomo"},{"id":"350281","latitude":"-2.01027780","longitude":"15.13833330","name":"Mbon"},{"id":"350291","latitude":"-2.91555560","longitude":"15.63583330","name":"Mbouamb\u00e9"},{"id":"350292","latitude":"-1.73083330","longitude":"15.23916670","name":"Mboub\u00e9"},{"id":"350293","latitude":"-1.51527780","longitude":"15.39277780","name":"Mboub\u00e9-Ondzala"},{"id":"350294","latitude":"-1.73083330","longitude":"15.23916670","name":"M'Boubou"},{"id":"350305","latitude":"-1.63277780","longitude":"16.00888890","name":"Mboul\u00e9mo"},{"id":"350307","latitude":"-1.31611110","longitude":"16.17833330","name":"M'Bouli"},{"id":"350335","latitude":"-1.60138890","longitude":"16.49027780","name":"M\u00e9kala"},{"id":"350343","latitude":"-2.36555560","longitude":"16.10722220","name":"M\u00e9libou"},{"id":"350347","latitude":"-1.91388890","longitude":"16.31416670","name":"Menboua"},{"id":"350352","latitude":"-1.92111110","longitude":"15.02916670","name":"Mengo"},{"id":"350355","latitude":"-2.20000000","longitude":"14.40000000","name":"M\u00e9ragna"},{"id":"350357","latitude":"-1.40638890","longitude":"16.19472220","name":"Messimba"},{"id":"350364","latitude":"-2.32250000","longitude":"14.60277780","name":"M'Foa"},{"id":"350365","latitude":"-2.32250000","longitude":"14.60277780","name":"Mfoua"},{"id":"350367","latitude":"-2.35333330","longitude":"14.91972220","name":"Mfou"},{"id":"350370","latitude":"-2.40777780","longitude":"15.77166670","name":"Mfoura"},{"id":"350394","latitude":"-2.27111110","longitude":"14.40305560","name":"Mi\u00e9l\u00e9"},{"id":"350468","latitude":"-1.92111110","longitude":"15.02916670","name":"Mingo"},{"id":"350520","latitude":"-1.83555560","longitude":"16.31583330","name":"Mit\u00e9 Mit\u00e9"},{"id":"350547","latitude":"-1.84388890","longitude":"15.40916670","name":"Moa"},{"id":"350565","latitude":"-1.78333330","longitude":"16.45000000","name":"Mobembo"},{"id":"350594","latitude":"-1.36805560","longitude":"15.19361110","name":"Moka"},{"id":"350638","latitude":"-1.55694440","longitude":"16.39583330","name":"Moloko"},{"id":"350639","latitude":"-1.48194440","longitude":"16.13861110","name":"Molomo"},{"id":"350652","latitude":"-1.76861110","longitude":"16.23861110","name":"Mompouo"},{"id":"350665","latitude":"-2.73750000","longitude":"16.18527780","name":"Mongania"},{"id":"350667","latitude":"-2.42611110","longitude":"16.14388890","name":"Mongolo"},{"id":"350680","latitude":"-1.81138890","longitude":"15.46944440","name":"Moni"},{"id":"350688","latitude":"-1.76861110","longitude":"16.23861110","name":"Mopombo"},{"id":"350701","latitude":"-1.47833330","longitude":"15.92861110","name":"Mosind\u00e9"},{"id":"350708","latitude":"-1.47833330","longitude":"15.92861110","name":"Mossend\u00e9"},{"id":"350721","latitude":"-2.43166670","longitude":"14.45888890","name":"Motendzi"},{"id":"350724","latitude":"-1.55694440","longitude":"16.39583330","name":"Motoko"},{"id":"350725","latitude":"-1.86944440","longitude":"16.30777780","name":"Motokoumba"},{"id":"350728","latitude":"-1.86944440","longitude":"16.30777780","name":"Motoukamba"},{"id":"350744","latitude":"-2.48333330","longitude":"15.75000000","name":"Mouarri"},{"id":"350761","latitude":"-1.81138890","longitude":"15.46944440","name":"Moudni"},{"id":"350788","latitude":"-1.63277780","longitude":"15.94194440","name":"Moui"},{"id":"350911","latitude":"-1.81138890","longitude":"15.46944440","name":"Mouoni"},{"id":"351023","latitude":"-2.30388890","longitude":"14.37888890","name":"Mouyali"},{"id":"351059","latitude":"-2.93250000","longitude":"16.16305560","name":"Mpala-L\u00e9fini"},{"id":"351060","latitude":"-1.82222220","longitude":"16.21916670","name":"Mpala"},{"id":"351063","latitude":"-1.69527780","longitude":"16.01611110","name":"Mpama"},{"id":"351064","latitude":"-1.59972220","longitude":"15.21694440","name":"Mpana"},{"id":"351065","latitude":"-1.59972220","longitude":"15.21694440","name":"M'Pana"},{"id":"351067","latitude":"-1.58638890","longitude":"15.77638890","name":"Mpan"},{"id":"351069","latitude":"-1.45583330","longitude":"15.88972220","name":"Mpasa"},{"id":"351079","latitude":"-2.72916670","longitude":"15.26972220","name":"Mpe"},{"id":"351089","latitude":"-2.40111110","longitude":"14.57416670","name":"Mpini"},{"id":"351090","latitude":"-1.95583330","longitude":"15.02333330","name":"Mpira"},{"id":"351095","latitude":"-2.40222220","longitude":"15.49638890","name":"Mpo"},{"id":"351096","latitude":"-2.15277780","longitude":"15.05277780","name":"Mpon"},{"id":"351100","latitude":"-2.37388890","longitude":"14.89638890","name":"Mpouandzio"},{"id":"351101","latitude":"-1.75750000","longitude":"16.04138890","name":"Mpouaya"},{"id":"351103","latitude":"-2.61500000","longitude":"16.21777780","name":"Mpou\u00efa"},{"id":"351104","latitude":"-2.35944440","longitude":"14.48861110","name":"Mpoukou"},{"id":"351109","latitude":"-1.97777780","longitude":"16.04166670","name":"Mpounou"},{"id":"351112","latitude":"-2.68000000","longitude":"16.21083330","name":"Mpouya Mok\u00e9"},{"id":"351114","latitude":"-2.61500000","longitude":"16.21777780","name":"Mpouya"},{"id":"351137","latitude":"-2.02277780","longitude":"15.71055560","name":"Mwa"},{"id":"351140","latitude":"-1.81138890","longitude":"15.46944440","name":"Mwoni"},{"id":"351155","latitude":"-1.69361110","longitude":"16.07194440","name":"Ndaba"},{"id":"351180","latitude":"-2.20250000","longitude":"16.08833330","name":"Ndolo"},{"id":"351196","latitude":"-1.29694440","longitude":"15.56750000","name":"Ndouomi"},{"id":"351201","latitude":"-2.36472220","longitude":"14.51222220","name":"Ndzi\u00e9g\u00e9"},{"id":"351202","latitude":"-1.52750000","longitude":"15.00527780","name":"Ndzongo"},{"id":"351203","latitude":"-1.52750000","longitude":"15.00527780","name":"N'Dzongo"},{"id":"351212","latitude":"-2.28722220","longitude":"14.48388890","name":"Ngakili"},{"id":"351213","latitude":"-1.47583330","longitude":"15.12250000","name":"Ngakoma"},{"id":"351232","latitude":"-1.47305560","longitude":"15.54361110","name":"Nganba"},{"id":"351244","latitude":"-1.43500000","longitude":"16.06888890","name":"Ngania"},{"id":"351246","latitude":"-2.37611110","longitude":"14.45194440","name":"Ngani"},{"id":"351247","latitude":"-1.53944440","longitude":"15.94277780","name":"Ngan"},{"id":"351250","latitude":"-2.48722220","longitude":"15.75555560","name":"N'Gao"},{"id":"351261","latitude":"-2.57444440","longitude":"16.18916670","name":"Ng\u00e9k\u00e9"},{"id":"351265","latitude":"-1.36250000","longitude":"16.01555560","name":"Ng\u00e9l\u00e9"},{"id":"351266","latitude":"-1.44333330","longitude":"16.08750000","name":"Ng\u00e9l\u00e9 Okasa"},{"id":"351268","latitude":"-1.79694440","longitude":"16.42555560","name":"Ngiabomb\u00e9"},{"id":"351274","latitude":"-1.94833330","longitude":"15.87472220","name":"Ngobana"},{"id":"351280","latitude":"-2.66111110","longitude":"15.59277780","name":"Ngo II"},{"id":"351304","latitude":"-2.48722220","longitude":"15.75555560","name":"Ngo"},{"id":"351315","latitude":"-1.98611110","longitude":"14.79944440","name":"Ngouananka"},{"id":"351335","latitude":"-1.36638890","longitude":"15.90500000","name":"Ngou\u00e9n\u00e9"},{"id":"351337","latitude":"-2.25472220","longitude":"16.07250000","name":"Ngouind\u00e9"},{"id":"351338","latitude":"-1.67305560","longitude":"15.95694440","name":"Ngouin"},{"id":"351339","latitude":"-1.67305560","longitude":"15.95694440","name":"N'Gouin"},{"id":"351340","latitude":"-1.68805560","longitude":"15.94916670","name":"Ngouin"},{"id":"351342","latitude":"-2.41722220","longitude":"14.58472220","name":"Ngoulonkila"},{"id":"351398","latitude":"-1.66000000","longitude":"16.31666670","name":"Nkala"},{"id":"351402","latitude":"-1.59222220","longitude":"15.03222220","name":"Nkana"},{"id":"351404","latitude":"-2.25305560","longitude":"15.01277780","name":"Nkanan"},{"id":"351405","latitude":"-1.97361110","longitude":"16.28916670","name":"Nkangakanga"},{"id":"351407","latitude":"-2.08555560","longitude":"15.87694440","name":"Nkan"},{"id":"351408","latitude":"-2.46000000","longitude":"14.90750000","name":"N'Kaon"},{"id":"351409","latitude":"-2.48444440","longitude":"16.16277780","name":"Nkasa"},{"id":"351411","latitude":"-1.51722220","longitude":"15.93333330","name":"Nkaye"},{"id":"351412","latitude":"-1.51722220","longitude":"15.93333330","name":"N'Kaye"},{"id":"351432","latitude":"-1.36500000","longitude":"15.46166670","name":"Nkolo"},{"id":"351437","latitude":"-1.54111110","longitude":"16.39972220","name":"Nkonga"},{"id":"351438","latitude":"-1.78694440","longitude":"15.86805560","name":"Nko"},{"id":"351439","latitude":"-1.78694440","longitude":"15.86805560","name":"N'Ko"},{"id":"351441","latitude":"-1.66138890","longitude":"15.68666670","name":"Nkono"},{"id":"351442","latitude":"-1.66138890","longitude":"15.68666670","name":"N'Kono"},{"id":"351443","latitude":"-1.88333330","longitude":"14.86055560","name":"Nkonou"},{"id":"351450","latitude":"-2.35722220","longitude":"14.45361110","name":"Nkoua"},{"id":"351457","latitude":"-1.08555560","longitude":"15.72750000","name":"Nkoulou"},{"id":"351458","latitude":"-1.08555560","longitude":"15.72750000","name":"N'Koulou"},{"id":"351459","latitude":"-1.34500000","longitude":"15.45944440","name":"Nkoulou"},{"id":"351460","latitude":"-2.23000000","longitude":"15.46888890","name":"Nkoumou"},{"id":"351462","latitude":"-1.76666670","longitude":"16.32583330","name":"Nkounda"},{"id":"351477","latitude":"-1.32666670","longitude":"16.03083330","name":"Npoumou"},{"id":"351478","latitude":"-2.61500000","longitude":"16.21777780","name":"N'Pouya"},{"id":"351479","latitude":"-2.35055560","longitude":"15.33472220","name":"Nsah"},{"id":"351483","latitude":"-2.35055560","longitude":"15.33472220","name":"Nsa"},{"id":"351491","latitude":"-2.94333330","longitude":"14.31472220","name":"Ntala"},{"id":"351492","latitude":"-1.72361110","longitude":"14.76805560","name":"Ntalla"},{"id":"351499","latitude":"-2.37944440","longitude":"14.53805560","name":"Ntchoumou"},{"id":"351519","latitude":"-1.37222220","longitude":"15.45916670","name":"Ntou II"},{"id":"351520","latitude":"-1.41222220","longitude":"15.44388890","name":"Ntou"},{"id":"351521","latitude":"-1.41222220","longitude":"15.44388890","name":"N'Tou"},{"id":"351533","latitude":"-1.75222220","longitude":"15.93138890","name":"Ntsou"},{"id":"351534","latitude":"-1.85361110","longitude":"16.05888890","name":"Ntswankan"},{"id":"351539","latitude":"-1.95638890","longitude":"16.18555560","name":"Nzabi"},{"id":"351548","latitude":"-1.94416670","longitude":"16.29000000","name":"Nzalokw\u00e9"},{"id":"351582","latitude":"-1.99500000","longitude":"16.17666670","name":"Obaba III"},{"id":"351583","latitude":"-1.98666670","longitude":"16.19111110","name":"Obaba II"},{"id":"351584","latitude":"-1.97611110","longitude":"16.19111110","name":"Obaba"},{"id":"351586","latitude":"-1.55388890","longitude":"15.93583330","name":"Obala II"},{"id":"351587","latitude":"-1.51194440","longitude":"15.83805560","name":"Obala I"},{"id":"351590","latitude":"-1.51194440","longitude":"15.83805560","name":"Obala"},{"id":"351592","latitude":"-1.83861110","longitude":"15.83916670","name":"Obana"},{"id":"351595","latitude":"-1.60944440","longitude":"15.49527780","name":"Oban"},{"id":"351596","latitude":"-1.42444440","longitude":"15.97250000","name":"Obas\u00e9n\u00e9"},{"id":"351597","latitude":"-1.31388890","longitude":"15.34111110","name":"Ob\u00e9a"},{"id":"351598","latitude":"-1.00000000","longitude":"15.61833330","name":"Ob\u00e9k\u00e9"},{"id":"351599","latitude":"-1.26555560","longitude":"15.46305560","name":"Obelango"},{"id":"351601","latitude":"-1.26555560","longitude":"15.46305560","name":"Ob\u00e9lingo"},{"id":"351604","latitude":"-1.14250000","longitude":"15.64916670","name":"Obeme"},{"id":"351605","latitude":"-1.60805560","longitude":"16.14222220","name":"Obenza"},{"id":"351613","latitude":"-1.55888890","longitude":"15.80138890","name":"Obilaboma"},{"id":"351614","latitude":"-1.73361110","longitude":"16.03000000","name":"Obilanboma II"},{"id":"351615","latitude":"-1.69666670","longitude":"16.05888890","name":"Obilanboma"},{"id":"351618","latitude":"-1.53361110","longitude":"15.60027780","name":"Obili"},{"id":"351620","latitude":"-1.60805560","longitude":"16.14222220","name":"Obindza"},{"id":"351625","latitude":"-1.73694440","longitude":"14.98722220","name":"Oboli"},{"id":"351632","latitude":"-1.12611110","longitude":"15.67750000","name":"Obo"},{"id":"351633","latitude":"-1.68138890","longitude":"16.09444440","name":"Oboo"},{"id":"351634","latitude":"-1.93361110","longitude":"14.79972220","name":"Oboti"},{"id":"351642","latitude":"-1.28722220","longitude":"15.90000000","name":"Obouya"},{"id":"351643","latitude":"-1.31972220","longitude":"16.20750000","name":"Ochend\u00e9"},{"id":"351651","latitude":"-1.38194440","longitude":"15.56694440","name":"Odjika"},{"id":"351652","latitude":"-1.69444440","longitude":"15.48527780","name":"Odjoul\u00e9"},{"id":"351653","latitude":"-1.69444440","longitude":"15.48527780","name":"Odjouli"},{"id":"351660","latitude":"-1.25777780","longitude":"16.06055560","name":"Odzandongo"},{"id":"351661","latitude":"-1.54638890","longitude":"16.01361110","name":"Odzatoni"},{"id":"351662","latitude":"-1.25777780","longitude":"16.06055560","name":"Odzendongo"},{"id":"351663","latitude":"-2.16222220","longitude":"15.05138890","name":"Odzianti"},{"id":"351666","latitude":"-1.38194440","longitude":"15.56694440","name":"Odzika"},{"id":"351667","latitude":"-2.46666670","longitude":"14.70888890","name":"Odzion"},{"id":"351668","latitude":"-1.69444440","longitude":"15.48527780","name":"Odzoul"},{"id":"351669","latitude":"-1.60055560","longitude":"15.97888890","name":"Ofoundou"},{"id":"351670","latitude":"-1.84361110","longitude":"16.07361110","name":"Ofounou"},{"id":"351682","latitude":"-1.04250000","longitude":"15.59444440","name":"Okaga"},{"id":"351683","latitude":"-1.50055560","longitude":"15.99111110","name":"Oka\u00ef"},{"id":"351685","latitude":"-1.47444440","longitude":"15.10583330","name":"Okali"},{"id":"351686","latitude":"-1.23638890","longitude":"15.51111110","name":"Okamamou\u00e9"},{"id":"351687","latitude":"-1.23638890","longitude":"15.51111110","name":"Okamamw\u00e9"},{"id":"351689","latitude":"-1.53333330","longitude":"15.71694440","name":"Okamou\u00e9"},{"id":"351690","latitude":"-1.54194440","longitude":"15.79833330","name":"Okamw\u00e9"},{"id":"351696","latitude":"-1.56361110","longitude":"15.70138890","name":"Okango"},{"id":"351699","latitude":"-1.65722220","longitude":"15.30083330","name":"Oka"},{"id":"351701","latitude":"-2.46666670","longitude":"15.86666670","name":"Okari"},{"id":"351702","latitude":"-1.44361110","longitude":"15.94111110","name":"Okasa"},{"id":"351705","latitude":"-1.45888890","longitude":"16.07222220","name":"Okassa"},{"id":"351706","latitude":"-1.28305560","longitude":"15.36583330","name":"Okaya"},{"id":"351707","latitude":"-1.50055560","longitude":"15.99111110","name":"Okaye"},{"id":"351709","latitude":"-1.00000000","longitude":"15.61833330","name":"Ok\u00e9ke"},{"id":"351713","latitude":"-1.24194440","longitude":"15.59805560","name":"Ok\u00e9l\u00e9"},{"id":"351714","latitude":"-1.55000000","longitude":"15.76722220","name":"Okiala"},{"id":"351718","latitude":"-2.68777780","longitude":"15.29722220","name":"Oki\u00e9l\u00e9"},{"id":"351719","latitude":"-2.36000000","longitude":"15.46027780","name":"Oki\u00e9n\u00e9"},{"id":"351722","latitude":"-2.42805560","longitude":"14.56000000","name":"Okilandzouli"},{"id":"351726","latitude":"-1.04055560","longitude":"15.52888890","name":"Okogo"},{"id":"351731","latitude":"-2.02972220","longitude":"15.65583330","name":"Okomw\u00e9"},{"id":"351735","latitude":"-1.37555560","longitude":"15.68444440","name":"Okondo"},{"id":"351737","latitude":"-1.35194440","longitude":"15.39888890","name":"Okonga"},{"id":"351739","latitude":"-1.04055560","longitude":"15.52888890","name":"Okongo"},{"id":"351740","latitude":"-2.14250000","longitude":"15.91638890","name":"Okonkiou"},{"id":"351741","latitude":"-2.02972220","longitude":"15.65583330","name":"Okonmw\u00e9"},{"id":"351743","latitude":"-1.35222220","longitude":"15.83333330","name":"Oko"},{"id":"351745","latitude":"-1.74083330","longitude":"15.70194440","name":"Okouampi"},{"id":"351749","latitude":"-1.39388890","longitude":"15.62444440","name":"Okoubi"},{"id":"351756","latitude":"-1.10416670","longitude":"15.83416670","name":"Okouma"},{"id":"351760","latitude":"-1.01611110","longitude":"15.53250000","name":"Okounda"},{"id":"351761","latitude":"-1.21500000","longitude":"15.69388890","name":"Okoundou II"},{"id":"351762","latitude":"-1.19083330","longitude":"15.69972220","name":"Okoundou I"},{"id":"351763","latitude":"-1.19083330","longitude":"15.69972220","name":"Okoundou"},{"id":"351764","latitude":"-1.35194440","longitude":"15.39888890","name":"Okounga"},{"id":"351766","latitude":"-1.18194440","longitude":"15.87138890","name":"Okoungou"},{"id":"351768","latitude":"-1.93888890","longitude":"15.81194440","name":"Okouon"},{"id":"351769","latitude":"-2.22916670","longitude":"15.02083330","name":"Okoura"},{"id":"351772","latitude":"-1.74083330","longitude":"15.70194440","name":"Okwanpi"},{"id":"351774","latitude":"-1.17638890","longitude":"15.83416670","name":"Olana"},{"id":"351775","latitude":"-2.76444440","longitude":"15.52111110","name":"Olano"},{"id":"351779","latitude":"-2.32000000","longitude":"14.43361110","name":"Ol\u00e9l\u00e9"},{"id":"351780","latitude":"-1.14000000","longitude":"15.43611110","name":"Olemb\u00e9"},{"id":"351782","latitude":"-1.23416670","longitude":"15.90916670","name":"Ol\u00e9m\u00e9"},{"id":"351786","latitude":"-1.73361110","longitude":"16.03000000","name":"Olilamboma II"},{"id":"351787","latitude":"-1.69666670","longitude":"16.05888890","name":"Olilamboma I"},{"id":"351788","latitude":"-1.97305560","longitude":"16.14527780","name":"Oli"},{"id":"351797","latitude":"-1.27138890","longitude":"15.90000000","name":"Ollombo"},{"id":"351804","latitude":"-1.17444440","longitude":"15.53777780","name":"Olombo"},{"id":"351808","latitude":"-2.76444440","longitude":"15.52111110","name":"Olono"},{"id":"351812","latitude":"-2.04444440","longitude":"14.85472220","name":"Olouno"},{"id":"351813","latitude":"-2.21027780","longitude":"15.03500000","name":"Olounou I"},{"id":"351814","latitude":"-2.04444440","longitude":"14.85472220","name":"Olounou"},{"id":"351817","latitude":"-1.55750000","longitude":"15.69861110","name":"Olouo"},{"id":"351822","latitude":"-2.28444440","longitude":"15.82944440","name":"Ombima"},{"id":"351823","latitude":"-2.28444440","longitude":"15.82944440","name":"Ombina"},{"id":"351827","latitude":"-2.36666670","longitude":"15.80138890","name":"Om\u00e9inkou\u00e9r\u00e9"},{"id":"351848","latitude":"-1.84361110","longitude":"16.07361110","name":"Omphounou"},{"id":"351849","latitude":"-1.56972220","longitude":"15.61555560","name":"Omphourou"},{"id":"351854","latitude":"-1.72444440","longitude":"16.10444440","name":"Onan"},{"id":"351856","latitude":"-1.83111110","longitude":"15.82277780","name":"Ondaba"},{"id":"351864","latitude":"-1.80388890","longitude":"16.14861110","name":"Ondzala"},{"id":"351866","latitude":"-1.54638890","longitude":"16.01361110","name":"Ondzatounou"},{"id":"351867","latitude":"-1.80000000","longitude":"16.13333330","name":"Ondzela"},{"id":"351868","latitude":"-1.67833330","longitude":"16.11416670","name":"Ondzeli"},{"id":"351869","latitude":"-1.54138890","longitude":"15.89361110","name":"Ondzio"},{"id":"351870","latitude":"-1.56972220","longitude":"15.61555560","name":"Onfounou"},{"id":"351872","latitude":"-1.50361110","longitude":"15.80333330","name":"Ongali"},{"id":"351874","latitude":"-1.21444440","longitude":"15.63055560","name":"Ongend\u00e9"},{"id":"351877","latitude":"-2.41888890","longitude":"14.96472220","name":"Ongia"},{"id":"351878","latitude":"-1.62472220","longitude":"16.05277780","name":"Ongo III"},{"id":"351883","latitude":"-1.59138890","longitude":"16.01305560","name":"Ongonyi"},{"id":"351884","latitude":"-1.61166670","longitude":"16.04666670","name":"Ongo"},{"id":"351885","latitude":"-1.58805560","longitude":"15.94944440","name":"Ongouala"},{"id":"351888","latitude":"-1.16638890","longitude":"15.44166670","name":"Ongouli"},{"id":"351891","latitude":"-1.59138890","longitude":"16.01305560","name":"Ongouoni"},{"id":"351892","latitude":"-1.60055560","longitude":"15.54916670","name":"Ongoye"},{"id":"351893","latitude":"-1.61416670","longitude":"16.02416670","name":"Ongoy"},{"id":"351894","latitude":"-1.21444440","longitude":"15.63055560","name":"Onguend\u00e9"},{"id":"351897","latitude":"-2.41888890","longitude":"14.96472220","name":"Onguia"},{"id":"351901","latitude":"-1.58805560","longitude":"15.94944440","name":"Ongwala"},{"id":"351902","latitude":"-2.34722220","longitude":"15.81388890","name":"Onianva"},{"id":"351909","latitude":"-2.32361110","longitude":"14.54083330","name":"Onkala"},{"id":"351914","latitude":"-2.15527780","longitude":"15.86638890","name":"Onkey"},{"id":"351915","latitude":"-2.66916670","longitude":"15.30500000","name":"Onki\u00e9l\u00e9"},{"id":"351916","latitude":"-1.50527780","longitude":"15.91055560","name":"Onkonoso"},{"id":"351917","latitude":"-1.50527780","longitude":"15.91055560","name":"Onkonosso"},{"id":"351919","latitude":"-1.72444440","longitude":"16.10444440","name":"Onna"},{"id":"351921","latitude":"-2.24638890","longitude":"16.04888890","name":"Onoabi"},{"id":"351923","latitude":"-1.81472220","longitude":"16.08750000","name":"Onpouana"},{"id":"351924","latitude":"-1.76500000","longitude":"16.04972220","name":"Onsi"},{"id":"351925","latitude":"-2.42805560","longitude":"16.13361110","name":"Ontabi"},{"id":"351929","latitude":"-2.66361110","longitude":"15.36638890","name":"Ontchouo"},{"id":"351932","latitude":"-2.54666670","longitude":"15.08777780","name":"Onto"},{"id":"351933","latitude":"-2.30277780","longitude":"14.37250000","name":"Ontourou"},{"id":"351936","latitude":"-1.51527780","longitude":"15.39277780","name":"Onzala"},{"id":"351937","latitude":"-1.67833330","longitude":"16.11416670","name":"Onz\u00e9l\u00e9"},{"id":"351942","latitude":"-2.48333330","longitude":"14.83333330","name":"Opa"},{"id":"351955","latitude":"-1.26388890","longitude":"15.81944440","name":"Osaga"},{"id":"351956","latitude":"-1.36416670","longitude":"15.31611110","name":"Osangi"},{"id":"351957","latitude":"-1.57027780","longitude":"15.88666670","name":"Osao"},{"id":"351958","latitude":"-1.41333330","longitude":"15.67944440","name":"Osa"},{"id":"351959","latitude":"-1.43833330","longitude":"15.37138890","name":"Os\u00e9l\u00e9 II"},{"id":"351960","latitude":"-1.42972220","longitude":"15.42000000","name":"Os\u00e9l\u00e9-Mok\u00e9"},{"id":"351961","latitude":"-1.41222220","longitude":"15.34805560","name":"Os\u00e9l\u00e9"},{"id":"351962","latitude":"-2.42722220","longitude":"14.52944440","name":"Osianka"},{"id":"351963","latitude":"-2.39666670","longitude":"14.51750000","name":"Osia"},{"id":"351965","latitude":"-1.91055560","longitude":"15.87250000","name":"Osio"},{"id":"351967","latitude":"-1.09277780","longitude":"15.96555560","name":"Ossaga"},{"id":"351973","latitude":"-1.36416670","longitude":"15.31611110","name":"Ossangui"},{"id":"351974","latitude":"-1.41333330","longitude":"15.67944440","name":"Ossao"},{"id":"351976","latitude":"-1.63888890","longitude":"16.22805560","name":"Ossa"},{"id":"351979","latitude":"-1.41222220","longitude":"15.34805560","name":"Oss\u00e9l\u00e9"},{"id":"351983","latitude":"-1.91055560","longitude":"15.87250000","name":"Ossio"},{"id":"351990","latitude":"-2.42805560","longitude":"16.13361110","name":"Otabi"},{"id":"351993","latitude":"-1.86583330","longitude":"15.92777780","name":"Otala"},{"id":"351994","latitude":"-1.22944440","longitude":"15.79111110","name":"Otali"},{"id":"351999","latitude":"-2.03916670","longitude":"14.34138890","name":"Otana"},{"id":"352003","latitude":"-1.98361110","longitude":"14.75000000","name":"Otchalaka"},{"id":"352005","latitude":"-2.44250000","longitude":"14.98833330","name":"Otchouank\u00e9"},{"id":"352006","latitude":"-1.49972220","longitude":"15.43361110","name":"Otchouanoa"},{"id":"352007","latitude":"-1.98361110","longitude":"14.75000000","name":"Otchulaka"},{"id":"352008","latitude":"-2.27388890","longitude":"14.56083330","name":"Ot\u00e9k\u00e9"},{"id":"352012","latitude":"-1.85861110","longitude":"14.87138890","name":"Otogo"},{"id":"352014","latitude":"-2.20000000","longitude":"15.45000000","name":"Otou\u00e9n\u00e9"},{"id":"352015","latitude":"-2.30277780","longitude":"14.37250000","name":"Otourou"},{"id":"352016","latitude":"-2.04861110","longitude":"14.71861110","name":"Otsalaka"},{"id":"352017","latitude":"-1.82583330","longitude":"15.17555560","name":"Otsato"},{"id":"352019","latitude":"-1.07111110","longitude":"15.38583330","name":"Otsend\u00e9"},{"id":"352022","latitude":"-1.54611110","longitude":"16.06666670","name":"Otsiend\u00e9"},{"id":"352023","latitude":"-1.07111110","longitude":"15.38583330","name":"Otsind\u00e9"},{"id":"352024","latitude":"-1.50750000","longitude":"16.10833330","name":"Otsini"},{"id":"352025","latitude":"-1.20500000","longitude":"15.94305560","name":"Otsokia"},{"id":"352027","latitude":"-1.60277780","longitude":"15.49805560","name":"Otsouanta"},{"id":"352029","latitude":"-2.08972220","longitude":"15.59055560","name":"Ottui"},{"id":"352030","latitude":"-2.08972220","longitude":"15.59055560","name":"Otui"},{"id":"352031","latitude":"-1.54638890","longitude":"16.01361110","name":"Otzatounou"},{"id":"352032","latitude":"-1.38944440","longitude":"15.56861110","name":"Otzia"},{"id":"352040","latitude":"-1.67166670","longitude":"14.94500000","name":"Ouannaga"},{"id":"352047","latitude":"-2.35722220","longitude":"15.30666670","name":"Ou\u00e9ndz\u00e9"},{"id":"352067","latitude":"-2.44833330","longitude":"14.50138890","name":"Ovansoki"},{"id":"352071","latitude":"-1.56472220","longitude":"15.94666670","name":"Ow\u00e9"},{"id":"352073","latitude":"-1.56472220","longitude":"15.94666670","name":"Owou\u00e9"},{"id":"352074","latitude":"-1.33416670","longitude":"15.64444440","name":"Oyaba"},{"id":"352077","latitude":"-1.33416670","longitude":"15.64444440","name":"Oyala"},{"id":"352079","latitude":"-1.44444440","longitude":"15.42944440","name":"Oyali"},{"id":"352080","latitude":"-1.59694440","longitude":"15.98000000","name":"Oyama"},{"id":"352081","latitude":"-1.67166670","longitude":"14.94500000","name":"Oyananga"},{"id":"352083","latitude":"-1.59694440","longitude":"15.98000000","name":"Oyana"},{"id":"352094","latitude":"-2.38916670","longitude":"15.78944440","name":"Oyomfoula"},{"id":"352096","latitude":"-2.38916670","longitude":"15.78944440","name":"Oyonfoula"},{"id":"352098","latitude":"-1.07333330","longitude":"15.78000000","name":"Oyongo"},{"id":"352100","latitude":"-1.03333330","longitude":"15.66666670","name":"Oyo"},{"id":"352123","latitude":"-1.25833330","longitude":"16.03388890","name":"Pama"},{"id":"352130","latitude":"-1.75000000","longitude":"16.46666670","name":"Pampoko"},{"id":"352131","latitude":"-1.66055560","longitude":"15.30972220","name":"Pana"},{"id":"352159","latitude":"-1.45583330","longitude":"15.88972220","name":"Passa"},{"id":"352195","latitude":"-1.35861110","longitude":"16.27611110","name":"Pombo-Bouendza"},{"id":"352198","latitude":"-1.35861110","longitude":"16.27611110","name":"Pombo"},{"id":"352200","latitude":"-1.35861110","longitude":"16.27611110","name":"Ponbo"},{"id":"352208","latitude":"-1.11111110","longitude":"15.46944440","name":"Posi"},{"id":"352234","latitude":"-1.36305560","longitude":"15.93055560","name":"Pounamou\u00e9"},{"id":"352239","latitude":"-1.86972220","longitude":"15.99250000","name":"Pounou"},{"id":"352241","latitude":"-1.30555560","longitude":"15.71861110","name":"Pousou"},{"id":"352242","latitude":"-1.30555560","longitude":"15.71861110","name":"Poussou"},{"id":"352243","latitude":"-1.75750000","longitude":"16.04138890","name":"Pouyan"},{"id":"352265","latitude":"-2.48333330","longitude":"16.11666670","name":"Sako"},{"id":"352382","latitude":"-2.57777780","longitude":"16.19222220","name":"Talamich"},{"id":"352385","latitude":"-2.50583330","longitude":"14.70750000","name":"Talangai"},{"id":"352477","latitude":"-2.44250000","longitude":"14.98833330","name":"Tchouank\u00e9"},{"id":"352539","latitude":"-2.11166670","longitude":"15.07972220","name":"Tourn\u00e9"},{"id":"352544","latitude":"-1.34555560","longitude":"15.90722220","name":"Tsali"},{"id":"352550","latitude":"-1.80138890","longitude":"16.14472220","name":"Tsampoko"},{"id":"352551","latitude":"-1.84888890","longitude":"16.26222220","name":"Tsampokou"},{"id":"352552","latitude":"-1.84888890","longitude":"16.26222220","name":"Tsampoto"},{"id":"352559","latitude":"-1.35222220","longitude":"15.84361110","name":"Tsangi"},{"id":"352561","latitude":"-1.06750000","longitude":"15.51000000","name":"Tsani"},{"id":"352595","latitude":"-1.20500000","longitude":"15.94305560","name":"Tsokia"},{"id":"352605","latitude":"-1.85361110","longitude":"16.05888890","name":"Tsouankan"},{"id":"352607","latitude":"-1.28250000","longitude":"16.02638890","name":"Tsoulookasa"},{"id":"352612","latitude":"-1.54861110","longitude":"15.87083330","name":"Tsouo"},{"id":"352613","latitude":"-1.75222220","longitude":"15.93138890","name":"Tsou"},{"id":"352615","latitude":"-1.39055560","longitude":"16.14083330","name":"Tzodzo"},{"id":"352623","latitude":"-2.31250000","longitude":"14.60500000","name":"Vila"},{"id":"352626","latitude":"-2.57083330","longitude":"14.49722220","name":"Village Babinga"},{"id":"352641","latitude":"-2.51583330","longitude":"16.16833330","name":"Vono"},{"id":"352678","latitude":"-2.35722220","longitude":"15.30666670","name":"Wendz\u00e9"},{"id":"352680","latitude":"-1.70388890","longitude":"15.80305560","name":"Yaba II"},{"id":"352682","latitude":"-1.70694440","longitude":"15.79250000","name":"Yaba I"},{"id":"352685","latitude":"-1.04611110","longitude":"15.73638890","name":"Yaba"},{"id":"352693","latitude":"-1.59611110","longitude":"15.88500000","name":"Yala"},{"id":"352700","latitude":"-1.45583330","longitude":"15.15888890","name":"Yama"},{"id":"352751","latitude":"-2.64972220","longitude":"14.76611110","name":"Yili"},{"id":"352752","latitude":"-2.30638890","longitude":"14.44694440","name":"Yima"},{"id":"352762","latitude":"-2.45611110","longitude":"15.01611110","name":"Yonon"},{"id":"352766","latitude":"-2.28388890","longitude":"14.51222220","name":"Youlambali"}]