[{"id":"670704","latitude":"57.72166670","longitude":"26.51083330","name":"\u00c4hij\u00e4rve"},{"id":"670719","latitude":"57.85666670","longitude":"26.67055560","name":"Aidaku"},{"id":"670750","latitude":"57.87944440","longitude":"26.83666670","name":"Ala-J\u00e4rve"},{"id":"670751","latitude":"57.87944440","longitude":"26.83666670","name":"Ala-J\u00e4rvere"},{"id":"670758","latitude":"57.60000000","longitude":"26.53333330","name":"Alak\u00fcla"},{"id":"670761","latitude":"57.60000000","longitude":"26.53333330","name":"Alakyula"},{"id":"670767","latitude":"57.68333330","longitude":"27.13333330","name":"Ala-Suhka"},{"id":"670770","latitude":"57.83333330","longitude":"26.93333330","name":"Ala-Vagula"},{"id":"670857","latitude":"57.82444440","longitude":"27.40583330","name":"Andrikova"},{"id":"670891","latitude":"57.81472220","longitude":"26.45694440","name":"Anne"},{"id":"670906","latitude":"57.82555560","longitude":"26.54055560","name":"Antsen'"},{"id":"670907","latitude":"57.82555560","longitude":"26.54055560","name":"Antsla"},{"id":"670908","latitude":"57.85416670","longitude":"26.44750000","name":"Antsu"},{"id":"670909","latitude":"57.79194440","longitude":"27.22083330","name":"Antsum\u00e4e"},{"id":"670911","latitude":"57.82555560","longitude":"26.54055560","name":"Antzen"},{"id":"670915","latitude":"57.82555560","longitude":"26.54055560","name":"Anzen"},{"id":"671116","latitude":"57.83500000","longitude":"26.48083330","name":"Boose Asundus"},{"id":"671117","latitude":"57.83500000","longitude":"26.48083330","name":"Boose"},{"id":"671121","latitude":"57.83500000","longitude":"26.48083330","name":"Boze"},{"id":"671311","latitude":"57.82555560","longitude":"26.54055560","name":"Gauka"},{"id":"671324","latitude":"57.76361110","longitude":"26.50861110","name":"Haabsaare"},{"id":"671330","latitude":"57.72166670","longitude":"27.04888890","name":"Haanja"},{"id":"671342","latitude":"57.68888890","longitude":"27.22861110","name":"Haava"},{"id":"671364","latitude":"57.67222220","longitude":"26.97277780","name":"Haki"},{"id":"671373","latitude":"57.75194440","longitude":"27.19361110","name":"Halla"},{"id":"671384","latitude":"57.84166670","longitude":"26.76972220","name":"Hanike Asundus"},{"id":"671385","latitude":"57.84166670","longitude":"26.76972220","name":"H\u00e4nike"},{"id":"671395","latitude":"57.88416670","longitude":"26.66638890","name":"Hargi"},{"id":"671416","latitude":"57.81166670","longitude":"27.36555560","name":"H\u00e4rma"},{"id":"671422","latitude":"57.82555560","longitude":"26.54055560","name":"Hauka"},{"id":"671426","latitude":"57.69916670","longitude":"26.91777780","name":"Heibri"},{"id":"671431","latitude":"57.69305560","longitude":"27.27527780","name":"Heinasoo"},{"id":"671432","latitude":"57.69305560","longitude":"27.27527780","name":"Heinassoo"},{"id":"671437","latitude":"57.80111110","longitude":"27.51277780","name":"Helbi"},{"id":"671443","latitude":"57.82972220","longitude":"27.27944440","name":"Hellekunnu"},{"id":"671465","latitude":"57.82944440","longitude":"27.39555560","name":"Hilande"},{"id":"671476","latitude":"57.57472220","longitude":"27.23555560","name":"Hino"},{"id":"671477","latitude":"57.76638890","longitude":"27.20444440","name":"Hinsa"},{"id":"671478","latitude":"57.59583330","longitude":"26.70777780","name":"Hintsiko"},{"id":"671494","latitude":"57.71277780","longitude":"27.14111110","name":"Holdi"},{"id":"671496","latitude":"57.82194440","longitude":"27.13250000","name":"Hollopi"},{"id":"671497","latitude":"57.82194440","longitude":"27.13250000","name":"Holopi"},{"id":"671498","latitude":"57.76500000","longitude":"27.15111110","name":"Holsta"},{"id":"671501","latitude":"57.82194440","longitude":"27.13250000","name":"Holupi"},{"id":"671506","latitude":"57.63777780","longitude":"27.13138890","name":"Hulaku"},{"id":"671519","latitude":"57.71250000","longitude":"26.84194440","name":"Hurda"},{"id":"671522","latitude":"57.62388890","longitude":"26.59388890","name":"H\u00fcrova"},{"id":"671524","latitude":"57.84388890","longitude":"27.17222220","name":"Husari"},{"id":"671526","latitude":"57.60305560","longitude":"26.59055560","name":"H\u00fcti"},{"id":"671533","latitude":"57.72305560","longitude":"27.25750000","name":"Iedas"},{"id":"671564","latitude":"57.71361110","longitude":"27.32500000","name":"Illi"},{"id":"671656","latitude":"57.85000000","longitude":"26.68333330","name":"Jaago"},{"id":"671657","latitude":"57.85000000","longitude":"26.68333330","name":"Jaagu"},{"id":"671672","latitude":"57.74555560","longitude":"27.04416670","name":"Jaanim\u00e4e"},{"id":"671686","latitude":"57.70000000","longitude":"26.68333330","name":"Jakobi"},{"id":"671740","latitude":"57.75000000","longitude":"26.79583330","name":"J\u00e4rvepalu"},{"id":"671742","latitude":"57.84972220","longitude":"26.86888890","name":"J\u00e4rvere"},{"id":"671755","latitude":"57.72305560","longitude":"27.25750000","name":"Jeedask\u00fcla"},{"id":"671792","latitude":"57.75944440","longitude":"26.58250000","name":"J\u00f5epera"},{"id":"671805","latitude":"57.75944440","longitude":"26.58250000","name":"J\u00f5evera"},{"id":"671824","latitude":"57.77166670","longitude":"27.39000000","name":"J\u00f5ksi"},{"id":"671836","latitude":"57.82361110","longitude":"26.93555560","name":"Juba"},{"id":"671837","latitude":"57.69083330","longitude":"27.03111110","name":"Jugumetsa"},{"id":"671842","latitude":"57.74416670","longitude":"27.24138890","name":"Juraski"},{"id":"671855","latitude":"57.76666670","longitude":"27.28166670","name":"Kaagu"},{"id":"671870","latitude":"57.61972220","longitude":"27.11138890","name":"K\u00e4\u00e4nu"},{"id":"671871","latitude":"57.87083330","longitude":"27.10638890","name":"K\u00e4\u00e4pa"},{"id":"671873","latitude":"57.68277780","longitude":"27.06666670","name":"K\u00e4\u00e4raku"},{"id":"671903","latitude":"57.80055560","longitude":"26.93361110","name":"K\u00e4\u00e4tso"},{"id":"671934","latitude":"57.60166670","longitude":"27.16083330","name":"K\u00e4bli"},{"id":"671981","latitude":"57.76666670","longitude":"27.28166670","name":"Kagu"},{"id":"671990","latitude":"57.89972220","longitude":"26.76472220","name":"Kahro"},{"id":"672003","latitude":"57.75388890","longitude":"26.53027780","name":"Kaika"},{"id":"672035","latitude":"57.74111110","longitude":"27.41083330","name":"Kalatsova"},{"id":"672060","latitude":"57.61722220","longitude":"26.56861110","name":"Kallaste"},{"id":"672090","latitude":"57.78333330","longitude":"27.26666670","name":"Kamara"},{"id":"672126","latitude":"57.68694440","longitude":"26.72861110","name":"Kangsti"},{"id":"672140","latitude":"57.90666670","longitude":"27.13138890","name":"Kannu"},{"id":"672161","latitude":"57.76555560","longitude":"27.32305560","name":"Kapera"},{"id":"672202","latitude":"57.93000000","longitude":"26.69583330","name":"K\u00e4rgula Asundus"},{"id":"672203","latitude":"57.93000000","longitude":"26.69583330","name":"K\u00e4rgula"},{"id":"672208","latitude":"57.63250000","longitude":"27.19166670","name":"K\u00e4rina"},{"id":"672214","latitude":"57.55555560","longitude":"26.56000000","name":"Karis\u00f6\u00f6di"},{"id":"672253","latitude":"57.90305560","longitude":"27.02777780","name":"K\u00e4rnam\u00e4e"},{"id":"672300","latitude":"57.78416670","longitude":"27.03861110","name":"Kasaritsa"},{"id":"672322","latitude":"57.90861110","longitude":"26.47388890","name":"Kassi Asundus"},{"id":"672324","latitude":"57.90861110","longitude":"26.47388890","name":"Kassi"},{"id":"672356","latitude":"57.60083330","longitude":"27.18361110","name":"Kaubi"},{"id":"672364","latitude":"57.72388890","longitude":"26.80388890","name":"Kaugu"},{"id":"672388","latitude":"57.67388890","longitude":"26.92972220","name":"Kaveldi"},{"id":"672418","latitude":"57.83055560","longitude":"26.66944440","name":"Keema"},{"id":"672449","latitude":"57.63472220","longitude":"26.88777780","name":"Kellam\u00e4e"},{"id":"672467","latitude":"57.74000000","longitude":"27.46638890","name":"Kerba"},{"id":"672473","latitude":"57.78361110","longitude":"27.31666670","name":"Kerep\u00e4\u00e4lse"},{"id":"672474","latitude":"57.78361110","longitude":"27.31666670","name":"Kerepealse"},{"id":"672475","latitude":"57.78361110","longitude":"27.31666670","name":"Kerepyalse"},{"id":"672477","latitude":"57.72222220","longitude":"27.12527780","name":"Kergatsi"},{"id":"672535","latitude":"57.72166670","longitude":"27.04888890","name":"Khaan'ya"},{"id":"672554","latitude":"57.72166670","longitude":"27.04888890","name":"Khan'ya"},{"id":"672603","latitude":"57.76500000","longitude":"27.15111110","name":"Kholsta"},{"id":"672604","latitude":"57.82194440","longitude":"27.13250000","name":"Kholupi"},{"id":"672618","latitude":"57.84166670","longitude":"26.76972220","name":"Khyanike"},{"id":"672677","latitude":"57.72166670","longitude":"27.43055560","name":"Kiislova"},{"id":"672693","latitude":"57.71666670","longitude":"26.68888890","name":"Kikkaoja"},{"id":"672694","latitude":"57.82777780","longitude":"27.45694440","name":"Kiksova"},{"id":"672711","latitude":"57.62944440","longitude":"27.01250000","name":"Kilomani"},{"id":"672715","latitude":"57.59194440","longitude":"27.21833330","name":"Kimalase"},{"id":"672745","latitude":"57.91361110","longitude":"26.54472220","name":"Kirikuk\u00fcla"},{"id":"672751","latitude":"57.69611110","longitude":"27.24527780","name":"Kirikum\u00e4e"},{"id":"672775","latitude":"57.86888890","longitude":"26.99972220","name":"Kirump\u00e4\u00e4"},{"id":"672782","latitude":"57.76500000","longitude":"27.49472220","name":"Kitse"},{"id":"672810","latitude":"57.58277780","longitude":"27.31194440","name":"Kivioru"},{"id":"672861","latitude":"57.84194440","longitude":"26.46388890","name":"Kobela"},{"id":"672895","latitude":"57.65583330","longitude":"26.53000000","name":"Koemetsa"},{"id":"672903","latitude":"57.64277780","longitude":"26.88027780","name":"Kogire"},{"id":"672906","latitude":"57.64277780","longitude":"26.88027780","name":"Kogre"},{"id":"672942","latitude":"57.93500000","longitude":"26.53222220","name":"Koigu"},{"id":"672968","latitude":"57.71361110","longitude":"27.00111110","name":"Kokem\u00e4e"},{"id":"672994","latitude":"57.88027780","longitude":"26.51083330","name":"K\u00f5lbi"},{"id":"672997","latitude":"57.77388890","longitude":"27.06638890","name":"Kolepi"},{"id":"673020","latitude":"57.81583330","longitude":"26.55888890","name":"Kollino"},{"id":"673024","latitude":"57.78666670","longitude":"27.15166670","name":"Koloreino"},{"id":"673031","latitude":"57.76666670","longitude":"27.10000000","name":"Kolu"},{"id":"673075","latitude":"57.68388890","longitude":"27.19472220","name":"K\u00f5o"},{"id":"673132","latitude":"57.71055560","longitude":"26.71444440","name":"K\u00f5rgepalu"},{"id":"673136","latitude":"57.89500000","longitude":"27.26472220","name":"K\u00f5rgessaare"},{"id":"673153","latitude":"57.81194440","longitude":"27.47277780","name":"Korski"},{"id":"673164","latitude":"57.78388890","longitude":"27.34583330","name":"K\u00f5rve"},{"id":"673181","latitude":"57.81277780","longitude":"27.03694440","name":"Kose"},{"id":"673215","latitude":"57.93500000","longitude":"26.53222220","name":"Koygu"},{"id":"673228","latitude":"57.85000000","longitude":"26.55666670","name":"Kraavi"},{"id":"673229","latitude":"57.61277780","longitude":"26.83972220","name":"Krabi Asundus"},{"id":"673230","latitude":"57.61277780","longitude":"26.83972220","name":"Krabi"},{"id":"673246","latitude":"57.61111110","longitude":"27.34055560","name":"Kriiva"},{"id":"673280","latitude":"57.72611110","longitude":"27.47944440","name":"Kuige"},{"id":"673308","latitude":"57.60583330","longitude":"27.09694440","name":"Kuklase"},{"id":"673312","latitude":"57.72861110","longitude":"27.39805560","name":"Kuksina"},{"id":"673319","latitude":"57.74416670","longitude":"27.27388890","name":"K\u00fclaoru"},{"id":"673323","latitude":"57.89416670","longitude":"26.47888890","name":"Kuldre"},{"id":"673337","latitude":"57.79222220","longitude":"27.47000000","name":"K\u00fcllatova"},{"id":"673363","latitude":"57.70166670","longitude":"27.19250000","name":"K\u00fcndja"},{"id":"673507","latitude":"57.59388890","longitude":"26.54583330","name":"Kuutsi"},{"id":"673533","latitude":"57.87083330","longitude":"27.10638890","name":"Kyapa"},{"id":"673567","latitude":"57.88027780","longitude":"26.51083330","name":"Kyl'bi"},{"id":"673768","latitude":"57.86277780","longitude":"27.18416670","name":"Lasva Asundus"},{"id":"673769","latitude":"57.86277780","longitude":"27.18416670","name":"Lasva"},{"id":"673777","latitude":"57.93138890","longitude":"27.08388890","name":"Lauga"},{"id":"673795","latitude":"57.75527780","longitude":"26.86722220","name":"Lauri"},{"id":"673796","latitude":"57.60083330","longitude":"26.66500000","name":"Laurim\u00e4e"},{"id":"673837","latitude":"57.81666670","longitude":"26.60000000","name":"Leese"},{"id":"673850","latitude":"57.83611110","longitude":"27.09305560","name":"Lehemetsa"},{"id":"673871","latitude":"57.63083330","longitude":"27.32583330","name":"Leimani"},{"id":"673872","latitude":"57.63083330","longitude":"27.32583330","name":"Leiman"},{"id":"673879","latitude":"57.91527780","longitude":"26.78305560","name":"Leiso"},{"id":"673907","latitude":"57.59750000","longitude":"27.22388890","name":"Lemmatsi"},{"id":"673936","latitude":"57.54472220","longitude":"26.58611110","name":"Leppura"},{"id":"673958","latitude":"57.63083330","longitude":"27.32583330","name":"Leymani"},{"id":"673964","latitude":"57.81666670","longitude":"26.60000000","name":"Leze"},{"id":"673973","latitude":"57.60722220","longitude":"26.81361110","name":"Liguri"},{"id":"674019","latitude":"57.89777780","longitude":"26.82416670","name":"Lilli-Anne"},{"id":"674029","latitude":"57.80305560","longitude":"27.33805560","name":"Lindora"},{"id":"674030","latitude":"57.82083330","longitude":"27.38055560","name":"Lindsi"},{"id":"674037","latitude":"57.87888890","longitude":"26.72055560","name":"Linnam\u00e4e Asundus"},{"id":"674040","latitude":"57.87888890","longitude":"26.72055560","name":"Linnam\u00e4e"},{"id":"674056","latitude":"57.82083330","longitude":"27.38055560","name":"Lintsi"},{"id":"674063","latitude":"57.65222220","longitude":"26.84694440","name":"Listaku"},{"id":"674065","latitude":"57.75833330","longitude":"26.62750000","name":"Litsmetsa"},{"id":"674144","latitude":"57.78277780","longitude":"26.92250000","name":"Lompka"},{"id":"674171","latitude":"57.80222220","longitude":"27.22000000","name":"Loosi Asundus"},{"id":"674172","latitude":"57.80222220","longitude":"27.22000000","name":"Loosi"},{"id":"674173","latitude":"57.88583330","longitude":"26.98694440","name":"Loosu"},{"id":"674206","latitude":"57.62500000","longitude":"27.36138890","name":"Luhamaa"},{"id":"674207","latitude":"57.77222220","longitude":"26.69111110","name":"Luhametsa"},{"id":"674233","latitude":"57.88888890","longitude":"26.61472220","name":"L\u00fcmatu"},{"id":"674238","latitude":"57.77861110","longitude":"26.48611110","name":"Lusti"},{"id":"674260","latitude":"57.60861110","longitude":"26.72416670","name":"L\u00fc\u00fctsepa"},{"id":"674261","latitude":"57.62666670","longitude":"26.99444440","name":"Luutsniku"},{"id":"674339","latitude":"57.65055560","longitude":"27.34583330","name":"M\u00e4\u00e4si"},{"id":"674342","latitude":"57.89833330","longitude":"27.31000000","name":"Madala"},{"id":"674350","latitude":"57.82916670","longitude":"26.43388890","name":"Madise"},{"id":"674354","latitude":"57.89611110","longitude":"26.87694440","name":"M\u00e4e-J\u00e4rvere"},{"id":"674372","latitude":"57.60083330","longitude":"27.04916670","name":"M\u00e4emurati"},{"id":"674385","latitude":"57.83333330","longitude":"26.95000000","name":"M\u00e4e-Vagula"},{"id":"674404","latitude":"57.73083330","longitude":"26.47138890","name":"M\u00e4hkli"},{"id":"674443","latitude":"57.72833330","longitude":"27.13444440","name":"Mallika"},{"id":"674484","latitude":"57.68305560","longitude":"26.90111110","name":"M\u00e4rdi"},{"id":"674524","latitude":"57.65861110","longitude":"26.71250000","name":"Matsi"},{"id":"674531","latitude":"57.67638890","longitude":"27.27805560","name":"Mauri"},{"id":"674541","latitude":"57.79694440","longitude":"26.99833330","name":"Meegom\u00e4e"},{"id":"674542","latitude":"57.71138890","longitude":"27.39472220","name":"Meeksi Asundus"},{"id":"674544","latitude":"57.71138890","longitude":"27.39472220","name":"Meeksi"},{"id":"674545","latitude":"57.78722220","longitude":"26.98111110","name":"Meeliku"},{"id":"674561","latitude":"57.71138890","longitude":"27.39472220","name":"Meksi"},{"id":"674582","latitude":"57.74472220","longitude":"27.46083330","name":"Merem\u00e4e"},{"id":"674585","latitude":"57.74472220","longitude":"27.46083330","name":"Meremyaya"},{"id":"674589","latitude":"57.74472220","longitude":"27.46083330","name":"Merim\u00e4e"},{"id":"674663","latitude":"57.64472220","longitude":"26.75277780","name":"Metstaga"},{"id":"674666","latitude":"57.64472220","longitude":"26.75277780","name":"Metstoga"},{"id":"674683","latitude":"57.60222220","longitude":"27.23777780","name":"Misso Asundus"},{"id":"674684","latitude":"57.60916670","longitude":"27.26027780","name":"Missok\u00fcla"},{"id":"674685","latitude":"57.60222220","longitude":"27.23777780","name":"Misso"},{"id":"674715","latitude":"57.77333330","longitude":"27.10222220","name":"M\u00f5isam\u00e4e"},{"id":"674727","latitude":"57.66111110","longitude":"27.35527780","name":"Mokra"},{"id":"674728","latitude":"57.75694440","longitude":"27.01138890","name":"M\u00f5ksi"},{"id":"674733","latitude":"57.66277780","longitude":"27.27166670","name":"M\u00f6ldre"},{"id":"674736","latitude":"57.74611110","longitude":"27.35027780","name":"M\u00f6ldri"},{"id":"674741","latitude":"57.60916670","longitude":"26.61361110","name":"M\u00f5niste"},{"id":"674749","latitude":"57.69833330","longitude":"26.96666670","name":"M\u00f5\u00f5lu"},{"id":"674760","latitude":"57.90027780","longitude":"27.07916670","name":"M\u00f5rgi"},{"id":"674777","latitude":"57.73000000","longitude":"26.86000000","name":"Muhkametsa"},{"id":"674798","latitude":"57.56722220","longitude":"27.27777780","name":"Muraski"},{"id":"674800","latitude":"57.59194440","longitude":"27.06472220","name":"Murati"},{"id":"674815","latitude":"57.75972220","longitude":"26.88472220","name":"Mustahamba"},{"id":"674833","latitude":"57.91055560","longitude":"26.85000000","name":"Mustja"},{"id":"674852","latitude":"57.60944440","longitude":"26.75694440","name":"Mutemetsa"},{"id":"674882","latitude":"57.60083330","longitude":"27.04916670","name":"Myaemurati"},{"id":"674891","latitude":"57.83333330","longitude":"26.95000000","name":"Myae-Vagula"},{"id":"674917","latitude":"57.68305560","longitude":"26.90111110","name":"Myardi"},{"id":"674937","latitude":"57.60916670","longitude":"26.61361110","name":"Myniste"},{"id":"674946","latitude":"57.90027780","longitude":"27.07916670","name":"Myrgi"},{"id":"675050","latitude":"57.72166670","longitude":"27.04888890","name":"Myza Khan'ya"},{"id":"675090","latitude":"57.61277780","longitude":"26.83972220","name":"Myza Krabi"},{"id":"675110","latitude":"57.93000000","longitude":"26.69583330","name":"Myza Kyargula"},{"id":"675125","latitude":"57.86277780","longitude":"27.18416670","name":"Myza Lasva"},{"id":"675139","latitude":"57.87888890","longitude":"26.72055560","name":"Myza Linnamyae"},{"id":"675147","latitude":"57.80222220","longitude":"27.22000000","name":"Myza Lozi"},{"id":"675167","latitude":"57.60222220","longitude":"27.23777780","name":"Myza Misso"},{"id":"675217","latitude":"57.89222220","longitude":"27.18333330","name":"Myza Pindi"},{"id":"675261","latitude":"57.64000000","longitude":"27.08416670","name":"Myza Rogosi"},{"id":"675301","latitude":"57.74222220","longitude":"26.78416670","name":"Myza Syanna"},{"id":"675323","latitude":"57.74027780","longitude":"26.65555560","name":"Myza Tsoru"},{"id":"675341","latitude":"57.92222220","longitude":"26.58277780","name":"Myza Urvaste"},{"id":"675343","latitude":"57.74777780","longitude":"27.10333330","name":"Myza Us-Saluze"},{"id":"675346","latitude":"57.86388890","longitude":"26.61361110","name":"Myza Vabina"},{"id":"675353","latitude":"57.78416670","longitude":"27.03861110","name":"Myza Vana-Kazaritsa"},{"id":"675362","latitude":"57.67138890","longitude":"26.67250000","name":"Myza Vana-Roza"},{"id":"675363","latitude":"57.72361110","longitude":"27.21222220","name":"Myza Vana-Saluze"},{"id":"675368","latitude":"57.89083330","longitude":"27.01888890","name":"Myza Vana-Vyaymela"},{"id":"675377","latitude":"57.72638890","longitude":"27.35833330","name":"Myza Vastseliyna"},{"id":"675397","latitude":"57.68750000","longitude":"26.93222220","name":"Myza Viytina"},{"id":"675434","latitude":"57.52138890","longitude":"26.59472220","name":"Naha"},{"id":"675446","latitude":"57.52138890","longitude":"26.59472220","name":"Nakha"},{"id":"675487","latitude":"57.87750000","longitude":"26.94472220","name":"Navi"},{"id":"675521","latitude":"57.72972220","longitude":"27.29361110","name":"Neuhausen"},{"id":"675526","latitude":"57.72972220","longitude":"27.29361110","name":"Neygauzen"},{"id":"675564","latitude":"57.81333330","longitude":"27.15694440","name":"Nodaze"},{"id":"675567","latitude":"57.73527780","longitude":"26.94527780","name":"Nogo"},{"id":"675604","latitude":"57.83138890","longitude":"27.13527780","name":"N\u00f5nova"},{"id":"675605","latitude":"57.81333330","longitude":"27.15694440","name":"Noodase"},{"id":"675606","latitude":"57.81333330","longitude":"27.15694440","name":"Noodask\u00fcla"},{"id":"675612","latitude":"57.77833330","longitude":"26.94750000","name":"Nooska"},{"id":"675649","latitude":"57.77916670","longitude":"26.87277780","name":"Nursi"},{"id":"675699","latitude":"57.81027780","longitude":"27.44222220","name":"Obiniste"},{"id":"675700","latitude":"57.81027780","longitude":"27.44222220","name":"Obinitsa"},{"id":"675716","latitude":"57.80694440","longitude":"26.51833330","name":"Oe"},{"id":"675783","latitude":"57.92138890","longitude":"27.05722220","name":"Oleski"},{"id":"675869","latitude":"57.78583330","longitude":"27.23777780","name":"Ortuma"},{"id":"675872","latitude":"57.68333330","longitude":"26.95000000","name":"Orum\u00e4e"},{"id":"675873","latitude":"57.68333330","longitude":"26.95000000","name":"Orum\u00f5isa"},{"id":"675874","latitude":"57.70000000","longitude":"26.93333330","name":"Orumyae"},{"id":"675880","latitude":"57.68333330","longitude":"26.95000000","name":"Oru"},{"id":"675888","latitude":"57.78138890","longitude":"27.43611110","name":"Ostrova"},{"id":"675889","latitude":"57.88583330","longitude":"26.81972220","name":"Osula"},{"id":"675901","latitude":"57.78333330","longitude":"26.88333330","name":"Otsa"},{"id":"675986","latitude":"57.59722220","longitude":"26.84861110","name":"Paganamaa"},{"id":"676004","latitude":"57.62916670","longitude":"26.78250000","name":"P\u00e4hni"},{"id":"676012","latitude":"57.91666670","longitude":"27.18416670","name":"Paidra"},{"id":"676071","latitude":"57.75194440","longitude":"27.45416670","name":"Palande"},{"id":"676072","latitude":"57.72972220","longitude":"27.04416670","name":"Palanum\u00e4e"},{"id":"676076","latitude":"57.58916670","longitude":"26.53750000","name":"P\u00e4la"},{"id":"676097","latitude":"57.64333330","longitude":"26.97527780","name":"Palli"},{"id":"676103","latitude":"57.81000000","longitude":"27.09444440","name":"Palometsa"},{"id":"676104","latitude":"57.73000000","longitude":"27.52083330","name":"Palo"},{"id":"676105","latitude":"57.72833330","longitude":"27.16722220","name":"Paloveere"},{"id":"676107","latitude":"57.65194440","longitude":"27.29305560","name":"P\u00e4ltre"},{"id":"676108","latitude":"57.65194440","longitude":"27.29305560","name":"P\u00e4ltri"},{"id":"676185","latitude":"57.67138890","longitude":"27.15277780","name":"Pari"},{"id":"676192","latitude":"57.90972220","longitude":"26.98305560","name":"Parksepa"},{"id":"676194","latitude":"57.66583330","longitude":"26.88166670","name":"P\u00e4rlij\u00f5e"},{"id":"676195","latitude":"57.61694440","longitude":"26.64583330","name":"Parmupalu"},{"id":"676212","latitude":"57.65194440","longitude":"27.29305560","name":"P\u00e4rtli"},{"id":"676279","latitude":"57.57472220","longitude":"26.58444440","name":"Peebu"},{"id":"676318","latitude":"57.68333330","longitude":"26.51666670","name":"Peraj\u00e4rve"},{"id":"676326","latitude":"57.70861110","longitude":"27.25472220","name":"Perametsa"},{"id":"676327","latitude":"57.68333330","longitude":"26.51666670","name":"Perayarve"},{"id":"676356","latitude":"57.71500000","longitude":"27.17916670","name":"Petruse"},{"id":"676357","latitude":"57.71500000","longitude":"27.17916670","name":"Petruze"},{"id":"676374","latitude":"57.89583330","longitude":"26.50972220","name":"Pihleni"},{"id":"676391","latitude":"57.66833330","longitude":"27.11277780","name":"Piipsem\u00e4e"},{"id":"676405","latitude":"57.78555560","longitude":"26.73805560","name":"Piisi"},{"id":"676417","latitude":"57.87222220","longitude":"27.24750000","name":"Pikakannu"},{"id":"676468","latitude":"57.92777780","longitude":"27.10555560","name":"Pille"},{"id":"676478","latitude":"57.89222220","longitude":"27.18333330","name":"Pindi Asundus"},{"id":"676480","latitude":"57.89222220","longitude":"27.18333330","name":"Pindi"},{"id":"676513","latitude":"57.66888890","longitude":"27.08666670","name":"Plaani"},{"id":"676514","latitude":"57.70194440","longitude":"27.06111110","name":"Plaksi"},{"id":"676515","latitude":"57.74250000","longitude":"27.36416670","name":"Plessi"},{"id":"676571","latitude":"57.80638890","longitude":"27.48444440","name":"Polovina"},{"id":"676587","latitude":"57.65055560","longitude":"27.22666670","name":"P\u00f5nni"},{"id":"676644","latitude":"57.69527780","longitude":"27.14277780","name":"Pressi"},{"id":"676698","latitude":"57.79611110","longitude":"27.03888890","name":"Puiga"},{"id":"676735","latitude":"57.64472220","longitude":"26.62472220","name":"Punsa"},{"id":"676756","latitude":"57.85166670","longitude":"27.06833330","name":"Pusepa"},{"id":"676778","latitude":"57.85166670","longitude":"27.06833330","name":"Puusepa"},{"id":"676780","latitude":"57.79388890","longitude":"27.26750000","name":"Puutli"},{"id":"676796","latitude":"57.58916670","longitude":"26.53750000","name":"Pyala"},{"id":"676820","latitude":"57.65194440","longitude":"27.29305560","name":"Pyartli"},{"id":"676840","latitude":"57.65055560","longitude":"27.22666670","name":"Pynni"},{"id":"676869","latitude":"57.64750000","longitude":"27.04694440","name":"Raagi"},{"id":"676923","latitude":"57.64750000","longitude":"27.04694440","name":"Ragi"},{"id":"676950","latitude":"57.91972220","longitude":"26.93888890","name":"Raista"},{"id":"676951","latitude":"57.91972220","longitude":"26.93888890","name":"Raiste"},{"id":"676985","latitude":"57.56250000","longitude":"27.23222220","name":"Rammuka"},{"id":"677044","latitude":"57.79500000","longitude":"27.09833330","name":"R\u00e4po"},{"id":"677061","latitude":"57.74722220","longitude":"26.99222220","name":"Rasva"},{"id":"677077","latitude":"57.64611110","longitude":"26.71305560","name":"Raudsepa"},{"id":"677079","latitude":"57.72777780","longitude":"26.90972220","name":"Rauge"},{"id":"677100","latitude":"57.91972220","longitude":"26.93888890","name":"Rayste"},{"id":"677136","latitude":"57.88583330","longitude":"26.81972220","name":"Reinum\u00e4gi"},{"id":"677169","latitude":"57.88583330","longitude":"26.81972220","name":"Reynomyagi"},{"id":"677210","latitude":"57.72194440","longitude":"26.77555560","name":"Riitsilla"},{"id":"677219","latitude":"57.77888890","longitude":"26.60388890","name":"Rimmi"},{"id":"677228","latitude":"57.66388890","longitude":"26.84916670","name":"Ristem\u00e4e"},{"id":"677246","latitude":"57.59694440","longitude":"27.30055560","name":"Ritsiko"},{"id":"677264","latitude":"57.64000000","longitude":"27.08416670","name":"Rogosi Asundus"},{"id":"677265","latitude":"57.64000000","longitude":"27.08416670","name":"Rogosi"},{"id":"677290","latitude":"57.79722220","longitude":"27.43611110","name":"Rokina"},{"id":"677309","latitude":"57.74111110","longitude":"26.70944440","name":"Roosiku"},{"id":"677312","latitude":"57.84444440","longitude":"26.94611110","name":"Roosisaare"},{"id":"677342","latitude":"57.74722220","longitude":"26.99222220","name":"Rosva"},{"id":"677352","latitude":"57.72777780","longitude":"26.90972220","name":"R\u00f5uge"},{"id":"677363","latitude":"57.91361110","longitude":"26.64000000","name":"Ruhingu"},{"id":"677374","latitude":"57.90083330","longitude":"26.70916670","name":"Rummi"},{"id":"677387","latitude":"57.73611110","longitude":"27.40333330","name":"Rutsi"},{"id":"677390","latitude":"57.71972220","longitude":"26.92638890","name":"Ruuga"},{"id":"677394","latitude":"57.64000000","longitude":"27.08416670","name":"Ruusm\u00e4e"},{"id":"677395","latitude":"57.64000000","longitude":"27.08416670","name":"Ruusmyae"},{"id":"677397","latitude":"57.73611110","longitude":"27.40333330","name":"Ruutsi"},{"id":"677427","latitude":"57.72777780","longitude":"26.90972220","name":"Ryuge"},{"id":"677438","latitude":"57.74777780","longitude":"27.10333330","name":"Saaluse Asundus"},{"id":"677444","latitude":"57.69972220","longitude":"27.35055560","name":"Saarde"},{"id":"677488","latitude":"57.65833330","longitude":"26.80722220","name":"Sadrametsa"},{"id":"677528","latitude":"57.61388890","longitude":"26.54416670","name":"Sakurgi"},{"id":"677601","latitude":"57.74222220","longitude":"26.78416670","name":"S\u00e4nna Asundus"},{"id":"677602","latitude":"57.74222220","longitude":"26.78416670","name":"S\u00e4nna"},{"id":"677620","latitude":"57.82138890","longitude":"26.62055560","name":"S\u00e4re"},{"id":"677628","latitude":"57.61555560","longitude":"27.06805560","name":"Sarise"},{"id":"677631","latitude":"57.60472220","longitude":"26.53861110","name":"Saru"},{"id":"677690","latitude":"57.75277780","longitude":"26.68083330","name":"Savil\u00f6\u00f6vi"},{"id":"677693","latitude":"57.60000000","longitude":"27.31666670","name":"Savim\u00e4e"},{"id":"677754","latitude":"57.75305560","longitude":"27.47972220","name":"Serga"},{"id":"677789","latitude":"57.79361110","longitude":"27.06055560","name":"Sika"},{"id":"677816","latitude":"57.63750000","longitude":"26.55388890","name":"Singa"},{"id":"677860","latitude":"57.86666670","longitude":"26.90000000","name":"Soe"},{"id":"677879","latitude":"57.85000000","longitude":"26.82527780","name":"S\u00f5merpalu Asundus"},{"id":"677880","latitude":"57.85000000","longitude":"26.82527780","name":"S\u00f5merpalu"},{"id":"677903","latitude":"57.75388890","longitude":"27.05666670","name":"Soodi"},{"id":"677911","latitude":"57.80972220","longitude":"27.18833330","name":"Sook\u00fcla"},{"id":"677912","latitude":"57.62805560","longitude":"26.84333330","name":"Sool\u00e4tte"},{"id":"677915","latitude":"57.79166670","longitude":"26.53638890","name":"Soome"},{"id":"677999","latitude":"57.68361110","longitude":"27.12083330","name":"Suhka"},{"id":"678010","latitude":"57.91027780","longitude":"26.75583330","name":"Sulbi"},{"id":"678081","latitude":"57.80972220","longitude":"27.23194440","name":"Sutte"},{"id":"678170","latitude":"57.74222220","longitude":"26.78416670","name":"Syanna"},{"id":"678179","latitude":"57.85000000","longitude":"26.82527780","name":"Symerpalu"},{"id":"678197","latitude":"57.80611110","longitude":"27.42333330","name":"T\u00e4\u00e4glova"},{"id":"678207","latitude":"57.85083330","longitude":"26.50805560","name":"Taberlaane"},{"id":"678208","latitude":"57.81333330","longitude":"27.31305560","name":"Tabina"},{"id":"678222","latitude":"57.58250000","longitude":"26.75694440","name":"Tagakolga"},{"id":"678224","latitude":"57.90944440","longitude":"26.92666670","name":"Tagak\u00fcla"},{"id":"678305","latitude":"57.85027780","longitude":"27.14416670","name":"Tammeveski"},{"id":"678395","latitude":"57.74750000","longitude":"26.94916670","name":"Tautsa"},{"id":"678400","latitude":"57.64805560","longitude":"27.32083330","name":"Teaste"},{"id":"678413","latitude":"57.77777780","longitude":"27.34722220","name":"Tellaste"},{"id":"678429","latitude":"57.72888890","longitude":"27.43527780","name":"Teterova"},{"id":"678441","latitude":"57.63833330","longitude":"27.32583330","name":"Tiilike"},{"id":"678449","latitude":"57.58166670","longitude":"26.53333330","name":"Tiitsa"},{"id":"678458","latitude":"57.80472220","longitude":"27.18055560","name":"Tilga"},{"id":"678475","latitude":"57.63833330","longitude":"27.32583330","name":"Tiylike"},{"id":"678481","latitude":"57.77638890","longitude":"27.46388890","name":"Tobrova"},{"id":"678556","latitude":"57.78111110","longitude":"27.13111110","name":"Tootsi"},{"id":"678613","latitude":"57.72055560","longitude":"27.08222220","name":"Trolla"},{"id":"678619","latitude":"57.66611110","longitude":"27.35694440","name":"Tserepi"},{"id":"678620","latitude":"57.65916670","longitude":"27.20722220","name":"Tsiistre"},{"id":"678627","latitude":"57.75972220","longitude":"27.42000000","name":"Tsirgu"},{"id":"678632","latitude":"57.92361110","longitude":"27.11888890","name":"Tsolgo"},{"id":"678633","latitude":"57.92361110","longitude":"27.11888890","name":"Tsolgu"},{"id":"678634","latitude":"57.75222220","longitude":"27.24361110","name":"Tsolli"},{"id":"678635","latitude":"57.74027780","longitude":"26.65555560","name":"Tsooru Asundus"},{"id":"678636","latitude":"57.74027780","longitude":"26.65555560","name":"Tsooru"},{"id":"678637","latitude":"57.74027780","longitude":"26.65555560","name":"Tsoru"},{"id":"678672","latitude":"57.58750000","longitude":"26.63833330","name":"Tundu"},{"id":"678691","latitude":"57.59000000","longitude":"26.50194440","name":"Tursa"},{"id":"678711","latitude":"57.66027780","longitude":"27.12611110","name":"Tuuka"},{"id":"678725","latitude":"57.80611110","longitude":"27.42333330","name":"Tyaglova"},{"id":"678801","latitude":"57.89194440","longitude":"26.56083330","name":"Uhtj\u00e4rve"},{"id":"678848","latitude":"57.82305560","longitude":"27.12277780","name":"Umbsaare"},{"id":"678904","latitude":"57.92222220","longitude":"26.58277780","name":"Urvaste Asundus"},{"id":"678907","latitude":"57.92222220","longitude":"26.58277780","name":"Urvaste"},{"id":"678921","latitude":"57.87388890","longitude":"26.73361110","name":"Utita"},{"id":"678930","latitude":"57.87722220","longitude":"26.54500000","name":"Uue-Antsla"},{"id":"678949","latitude":"57.74777780","longitude":"27.10333330","name":"Uue Saaluse"},{"id":"678980","latitude":"57.74777780","longitude":"27.10333330","name":"Uus Saaluse"},{"id":"678983","latitude":"57.76888890","longitude":"27.48361110","name":"Uusvada"},{"id":"678994","latitude":"57.86388890","longitude":"26.61361110","name":"Vaabina Asundus"},{"id":"678995","latitude":"57.86388890","longitude":"26.61361110","name":"Vaabina"},{"id":"679007","latitude":"57.78333330","longitude":"27.20861110","name":"Vaarkali"},{"id":"679028","latitude":"57.86472220","longitude":"26.89055560","name":"Vagula"},{"id":"679050","latitude":"57.72638890","longitude":"27.35833330","name":"Vahtseliina"},{"id":"679098","latitude":"57.89083330","longitude":"27.01888890","name":"V\u00e4imela Asundus"},{"id":"679099","latitude":"57.91972220","longitude":"26.93888890","name":"V\u00e4imela Suurk\u00fcla"},{"id":"679100","latitude":"57.89083330","longitude":"27.01888890","name":"V\u00e4imela"},{"id":"679112","latitude":"57.88055560","longitude":"27.05111110","name":"V\u00e4iso"},{"id":"679119","latitude":"57.73694440","longitude":"27.08972220","name":"Vakari"},{"id":"679200","latitude":"57.86611110","longitude":"26.53222220","name":"Vana-Antsla"},{"id":"679208","latitude":"57.78416670","longitude":"27.03861110","name":"Vana Kasaritsa Asundus"},{"id":"679209","latitude":"57.78416670","longitude":"27.03861110","name":"Vana-Kasaritsa"},{"id":"679250","latitude":"57.78972220","longitude":"26.93972220","name":"Vana-Nursi"},{"id":"679260","latitude":"57.67138890","longitude":"26.67250000","name":"Vana-Roosa Asundus"},{"id":"679261","latitude":"57.67138890","longitude":"26.67250000","name":"Vana-Roosa"},{"id":"679263","latitude":"57.72361110","longitude":"27.21222220","name":"Vana Saaluse Asundus"},{"id":"679264","latitude":"57.72361110","longitude":"27.21222220","name":"Vana-Saaluse"},{"id":"679275","latitude":"57.89083330","longitude":"27.01888890","name":"Vana-V\u00e4imela"},{"id":"679290","latitude":"57.89083330","longitude":"27.01888890","name":"Vana-Vyaymela"},{"id":"679338","latitude":"57.75000000","longitude":"27.46666670","name":"Varkali"},{"id":"679349","latitude":"57.63916670","longitude":"26.65972220","name":"Varstu"},{"id":"679377","latitude":"57.72638890","longitude":"27.35833330","name":"Vastseliina Asundus"},{"id":"679378","latitude":"57.72638890","longitude":"27.35833330","name":"Vastseliina"},{"id":"679379","latitude":"57.72638890","longitude":"27.35833330","name":"Vastselina"},{"id":"679380","latitude":"57.72638890","longitude":"27.35833330","name":"Vastseliyna"},{"id":"679386","latitude":"57.57361110","longitude":"26.67333330","name":"Vastse-Roosa"},{"id":"679395","latitude":"57.69583330","longitude":"27.31500000","name":"Vatsa"},{"id":"679477","latitude":"57.83388890","longitude":"27.01944440","name":"Verava"},{"id":"679480","latitude":"57.79694440","longitude":"27.49611110","name":"Veretina"},{"id":"679486","latitude":"57.80333330","longitude":"27.06861110","name":"Verij\u00e4rve"},{"id":"679489","latitude":"57.83388890","longitude":"27.01944440","name":"Veri"},{"id":"679493","latitude":"57.83388890","longitude":"27.01944440","name":"Verro"},{"id":"679495","latitude":"57.83388890","longitude":"27.01944440","name":"Veru"},{"id":"679550","latitude":"57.72583330","longitude":"26.65444440","name":"Viirapalu"},{"id":"679567","latitude":"57.68750000","longitude":"26.93222220","name":"Viitina Asundus"},{"id":"679568","latitude":"57.68750000","longitude":"26.93222220","name":"Viitina"},{"id":"679569","latitude":"57.68888890","longitude":"27.33250000","name":"Viitka"},{"id":"679602","latitude":"57.68638890","longitude":"27.08333330","name":"Villa"},{"id":"679604","latitude":"57.56333330","longitude":"26.51916670","name":"Villike"},{"id":"679624","latitude":"57.75000000","longitude":"27.50000000","name":"Vinski"},{"id":"679647","latitude":"57.73638890","longitude":"26.74527780","name":"Viru"},{"id":"679650","latitude":"57.88222220","longitude":"27.23750000","name":"Virve"},{"id":"679670","latitude":"57.68888890","longitude":"27.33250000","name":"Vitka"},{"id":"679738","latitude":"57.74000000","longitude":"27.15500000","name":"Voki"},{"id":"679748","latitude":"57.82777780","longitude":"26.98500000","name":"V\u00f5lsi"},{"id":"679751","latitude":"57.83111110","longitude":"27.54194440","name":"V\u00f5mmorski"},{"id":"679790","latitude":"57.85083330","longitude":"27.02277780","name":"V\u00f5rum\u00f5isa"},{"id":"679793","latitude":"57.82777780","longitude":"27.05055560","name":"V\u00f5rusoo"},{"id":"679794","latitude":"57.83388890","longitude":"27.01944440","name":"V\u00f5ru"},{"id":"679835","latitude":"57.89083330","longitude":"27.01888890","name":"Vyaymela"},{"id":"679863","latitude":"57.83388890","longitude":"27.01944440","name":"Vyru"},{"id":"679888","latitude":"57.83388890","longitude":"27.01944440","name":"Werro"},{"id":"679899","latitude":"57.83388890","longitude":"27.01944440","name":"W\u00f6ru"},{"id":"679904","latitude":"57.85000000","longitude":"26.68333330","name":"Yago"},{"id":"679905","latitude":"57.85000000","longitude":"26.68333330","name":"Yagu"},{"id":"679907","latitude":"57.70000000","longitude":"26.68333330","name":"Yakobi"}]